{
  "HHV31T": {
    "no_availability_all_day": false,
    "conflict_tijden": ""
  },
  "HHV44T": {
    "no_availability_all_day": false,
    "conflict_tijden": "07:00–11:48"
  },
  "HHV50T": {
    "no_availability_all_day": false,
    "conflict_tijden": ""
  },
  "HHV53T": {
    "no_availability_all_day": false,
    "conflict_tijden": "17:48–19:08, 07:15–11:48"
  },
  "HHV54T": {
    "no_availability_all_day": true,
    "conflict_tijden": "17:48–11:48"
  },
  "HHV61T": {
    "no_availability_all_day": false,
    "conflict_tijden": "17:48–18:52"
  },
  "HHV67T": {
    "no_availability_all_day": false,
    "conflict_tijden": ""
  },
  "HJD82F": {
    "no_availability_all_day": false,
    "conflict_tijden": ""
  },
  "J600HR": {
    "no_availability_all_day": false,
    "conflict_tijden": "17:48–10:46"
  },
  "J608HR": {
    "no_availability_all_day": true,
    "conflict_tijden": "17:48–11:48"
  },
  "JPD22G": {
    "no_availability_all_day": true,
    "conflict_tijden": "17:48–11:48"
  },
  "JPD48G": {
    "no_availability_all_day": false,
    "conflict_tijden": ""
  },
  "JPD51G": {
    "no_availability_all_day": true,
    "conflict_tijden": "17:48–11:48"
  },
  "JPD55G": {
    "no_availability_all_day": false,
    "conflict_tijden": ""
  },
  "JPD65G": {
    "no_availability_all_day": true,
    "conflict_tijden": "17:48–11:48"
  },
  "JPD81G": {
    "no_availability_all_day": true,
    "conflict_tijden": "17:48–11:48"
  },
  "JPD90G": {
    "no_availability_all_day": true,
    "conflict_tijden": "17:48–11:48"
  },
  "JRH24T": {
    "no_availability_all_day": true,
    "conflict_tijden": "17:48–11:48"
  },
  "JRH46T": {
    "no_availability_all_day": true,
    "conflict_tijden": "17:48–11:48"
  },
  "JRH50T": {
    "no_availability_all_day": false,
    "conflict_tijden": ""
  },
  "JRH58T": {
    "no_availability_all_day": false,
    "conflict_tijden": ""
  },
  "JRH59T": {
    "no_availability_all_day": false,
    "conflict_tijden": "17:48–19:08"
  },
  "JRH62T": {
    "no_availability_all_day": false,
    "conflict_tijden": "17:48–18:11"
  },
  "JRH63T": {
    "no_availability_all_day": false,
    "conflict_tijden": "09:00–11:48"
  },
  "JRH74T": {
    "no_availability_all_day": true,
    "conflict_tijden": "17:48–11:48"
  },
  "JRH85T": {
    "no_availability_all_day": false,
    "conflict_tijden": "17:48–19:05"
  },
  "K018JT": {
    "no_availability_all_day": true,
    "conflict_tijden": "17:48–11:48"
  },
  "K052FN": {
    "no_availability_all_day": false,
    "conflict_tijden": ""
  },
  "K218DF": {
    "no_availability_all_day": false,
    "conflict_tijden": "10:00–11:48"
  },
  "K398NP": {
    "no_availability_all_day": true,
    "conflict_tijden": "17:48–11:48"
  },
  "K405NP": {
    "no_availability_all_day": false,
    "conflict_tijden": ""
  },
  "K410NP": {
    "no_availability_all_day": false,
    "conflict_tijden": "17:48–00:15"
  },
  "K447NP": {
    "no_availability_all_day": false,
    "conflict_tijden": ""
  },
  "K454NP": {
    "no_availability_all_day": true,
    "conflict_tijden": "17:48–11:48"
  },
  "K491GV": {
    "no_availability_all_day": true,
    "conflict_tijden": "17:48–11:48"
  },
  "K502FN": {
    "no_availability_all_day": true,
    "conflict_tijden": "17:48–11:48"
  },
  "K506JK": {
    "no_availability_all_day": false,
    "conflict_tijden": ""
  },
  "K524JK": {
    "no_availability_all_day": false,
    "conflict_tijden": ""
  },
  "K525JK": {
    "no_availability_all_day": false,
    "conflict_tijden": ""
  },
  "K536JK": {
    "no_availability_all_day": false,
    "conflict_tijden": ""
  },
  "K558FN": {
    "no_availability_all_day": false,
    "conflict_tijden": "17:48–19:46"
  },
  "K648JH": {
    "no_availability_all_day": false,
    "conflict_tijden": ""
  },
  "K648SR": {
    "no_availability_all_day": false,
    "conflict_tijden": ""
  },
  "K649SR": {
    "no_availability_all_day": true,
    "conflict_tijden": "17:48–11:48"
  },
  "K656FF": {
    "no_availability_all_day": true,
    "conflict_tijden": "17:48–11:48"
  },
  "K657JH": {
    "no_availability_all_day": false,
    "conflict_tijden": "08:00–11:48"
  },
  "K745JH": {
    "no_availability_all_day": false,
    "conflict_tijden": ""
  },
  "K818JH": {
    "no_availability_all_day": false,
    "conflict_tijden": ""
  },
  "K971JS": {
    "no_availability_all_day": false,
    "conflict_tijden": "07:00–11:48"
  },
  "K981JS": {
    "no_availability_all_day": true,
    "conflict_tijden": "17:48–11:48"
  },
  "K996JS": {
    "no_availability_all_day": false,
    "conflict_tijden": ""
  },
  "L030GG": {
    "no_availability_all_day": false,
    "conflict_tijden": "09:00–11:48"
  },
  "L031GG": {
    "no_availability_all_day": true,
    "conflict_tijden": "17:48–11:48"
  },
  "L039GG": {
    "no_availability_all_day": false,
    "conflict_tijden": ""
  },
  "L041GG": {
    "no_availability_all_day": false,
    "conflict_tijden": ""
  },
  "L059ZR": {
    "no_availability_all_day": true,
    "conflict_tijden": "17:48–11:48"
  },
  "L085HG": {
    "no_availability_all_day": false,
    "conflict_tijden": ""
  },
  "L088HG": {
    "no_availability_all_day": false,
    "conflict_tijden": ""
  },
  "L091HG": {
    "no_availability_all_day": false,
    "conflict_tijden": ""
  },
  "L095HG": {
    "no_availability_all_day": false,
    "conflict_tijden": "18:44–19:45"
  },
  "L101ZP": {
    "no_availability_all_day": false,
    "conflict_tijden": ""
  },
  "L103ZP": {
    "no_availability_all_day": false,
    "conflict_tijden": ""
  },
  "L106ZP": {
    "no_availability_all_day": false,
    "conflict_tijden": "06:00–11:48"
  },
  "L108ZP": {
    "no_availability_all_day": false,
    "conflict_tijden": ""
  },
  "L120JB": {
    "no_availability_all_day": false,
    "conflict_tijden": ""
  },
  "L252NJ": {
    "no_availability_all_day": false,
    "conflict_tijden": "17:48–18:53"
  },
  "L254NJ": {
    "no_availability_all_day": false,
    "conflict_tijden": ""
  },
  "L375ST": {
    "no_availability_all_day": false,
    "conflict_tijden": ""
  },
  "L376ST": {
    "no_availability_all_day": false,
    "conflict_tijden": ""
  },
  "L513BP": {
    "no_availability_all_day": false,
    "conflict_tijden": "06:30–11:48"
  },
  "L538BK": {
    "no_availability_all_day": false,
    "conflict_tijden": ""
  },
  "L566PV": {
    "no_availability_all_day": true,
    "conflict_tijden": "17:48–11:48"
  },
  "L576PV": {
    "no_availability_all_day": false,
    "conflict_tijden": ""
  },
  "L588PV": {
    "no_availability_all_day": false,
    "conflict_tijden": ""
  },
  "L589PV": {
    "no_availability_all_day": false,
    "conflict_tijden": ""
  },
  "L626KP": {
    "no_availability_all_day": false,
    "conflict_tijden": ""
  },
  "L632KP": {
    "no_availability_all_day": false,
    "conflict_tijden": ""
  },
  "L638KP": {
    "no_availability_all_day": false,
    "conflict_tijden": ""
  },
  "L643KP": {
    "no_availability_all_day": true,
    "conflict_tijden": "17:48–11:48"
  },
  "L664FV": {
    "no_availability_all_day": false,
    "conflict_tijden": ""
  },
  "L665GR": {
    "no_availability_all_day": false,
    "conflict_tijden": "05:45–11:48"
  },
  "L697KP": {
    "no_availability_all_day": false,
    "conflict_tijden": "11:00–11:48"
  },
  "L835NR": {
    "no_availability_all_day": false,
    "conflict_tijden": ""
  },
  "L865GX": {
    "no_availability_all_day": false,
    "conflict_tijden": "08:15–11:48"
  },
  "L882NR": {
    "no_availability_all_day": true,
    "conflict_tijden": "17:48–11:48"
  },
  "L978NL": {
    "no_availability_all_day": false,
    "conflict_tijden": ""
  },
  "N061JD": {
    "no_availability_all_day": false,
    "conflict_tijden": ""
  },
  "N089KV": {
    "no_availability_all_day": false,
    "conflict_tijden": "11:15–11:48"
  },
  "N098BR": {
    "no_availability_all_day": false,
    "conflict_tijden": ""
  },
  "N141RD": {
    "no_availability_all_day": false,
    "conflict_tijden": ""
  },
  "N145RZ": {
    "no_availability_all_day": false,
    "conflict_tijden": "18:37–23:15"
  },
  "N155RD": {
    "no_availability_all_day": true,
    "conflict_tijden": "17:48–11:48"
  },
  "N159RZ": {
    "no_availability_all_day": true,
    "conflict_tijden": "17:48–11:48"
  },
  "N160RD": {
    "no_availability_all_day": false,
    "conflict_tijden": ""
  },
  "N165RZ": {
    "no_availability_all_day": false,
    "conflict_tijden": ""
  },
  "N187RD": {
    "no_availability_all_day": true,
    "conflict_tijden": "17:48–11:48"
  },
  "N200BH": {
    "no_availability_all_day": false,
    "conflict_tijden": ""
  },
  "N204HV": {
    "no_availability_all_day": false,
    "conflict_tijden": ""
  },
  "N217HV": {
    "no_availability_all_day": false,
    "conflict_tijden": ""
  },
  "N220DL": {
    "no_availability_all_day": false,
    "conflict_tijden": ""
  },
  "N225PF": {
    "no_availability_all_day": true,
    "conflict_tijden": "17:48–11:48"
  },
  "N236PF": {
    "no_availability_all_day": false,
    "conflict_tijden": "06:30–11:48"
  },
  "N248VT": {
    "no_availability_all_day": false,
    "conflict_tijden": ""
  },
  "N250VT": {
    "no_availability_all_day": false,
    "conflict_tijden": ""
  },
  "N251VT": {
    "no_availability_all_day": false,
    "conflict_tijden": ""
  },
  "N303VT": {
    "no_availability_all_day": false,
    "conflict_tijden": ""
  },
  "N308PS": {
    "no_availability_all_day": false,
    "conflict_tijden": "17:48–18:26, 08:00–11:00"
  },
  "N317PS": {
    "no_availability_all_day": false,
    "conflict_tijden": ""
  },
  "N318VT": {
    "no_availability_all_day": false,
    "conflict_tijden": "08:30–11:00"
  },
  "N331SF": {
    "no_availability_all_day": false,
    "conflict_tijden": ""
  },
  "N344RG": {
    "no_availability_all_day": true,
    "conflict_tijden": "17:48–11:48"
  },
  "N344SF": {
    "no_availability_all_day": false,
    "conflict_tijden": "00:45–06:15"
  },
  "N345SF": {
    "no_availability_all_day": false,
    "conflict_tijden": ""
  },
  "N360VT": {
    "no_availability_all_day": false,
    "conflict_tijden": ""
  },
  "N366RG": {
    "no_availability_all_day": false,
    "conflict_tijden": ""
  },
  "N377RG": {
    "no_availability_all_day": false,
    "conflict_tijden": "17:48–17:49, 10:30–11:48"
  },
  "N387VT": {
    "no_availability_all_day": false,
    "conflict_tijden": ""
  },
  "N397LD": {
    "no_availability_all_day": false,
    "conflict_tijden": ""
  },
  "N404LD": {
    "no_availability_all_day": false,
    "conflict_tijden": ""
  },
  "N406LD": {
    "no_availability_all_day": false,
    "conflict_tijden": ""
  },
  "N413LD": {
    "no_availability_all_day": false,
    "conflict_tijden": ""
  },
  "N414VT": {
    "no_availability_all_day": false,
    "conflict_tijden": "09:45–11:15"
  },
  "N453VT": {
    "no_availability_all_day": false,
    "conflict_tijden": "17:48–23:00"
  },
  "N489TF": {
    "no_availability_all_day": false,
    "conflict_tijden": ""
  },
  "N491NR": {
    "no_availability_all_day": false,
    "conflict_tijden": "18:30–22:00"
  },
  "N494TF": {
    "no_availability_all_day": true,
    "conflict_tijden": "17:48–11:48"
  },
  "N519DN": {
    "no_availability_all_day": true,
    "conflict_tijden": "17:48–11:48"
  },
  "N533VX": {
    "no_availability_all_day": false,
    "conflict_tijden": "17:48–21:45"
  },
  "N536VX": {
    "no_availability_all_day": false,
    "conflict_tijden": ""
  },
  "N560VX": {
    "no_availability_all_day": true,
    "conflict_tijden": "17:48–11:48"
  },
  "N565VX": {
    "no_availability_all_day": true,
    "conflict_tijden": "17:48–11:48"
  },
  "N576VX": {
    "no_availability_all_day": false,
    "conflict_tijden": ""
  },
  "N584NL": {
    "no_availability_all_day": false,
    "conflict_tijden": "17:48–18:52"
  },
  "N587NL": {
    "no_availability_all_day": false,
    "conflict_tijden": ""
  },
  "N602PD": {
    "no_availability_all_day": false,
    "conflict_tijden": "17:48–01:00, 08:45–11:48"
  },
  "N607NV": {
    "no_availability_all_day": false,
    "conflict_tijden": "09:30–11:45"
  },
  "N609PD": {
    "no_availability_all_day": true,
    "conflict_tijden": "17:48–11:48"
  },
  "N647NV": {
    "no_availability_all_day": false,
    "conflict_tijden": ""
  },
  "N669LK": {
    "no_availability_all_day": false,
    "conflict_tijden": ""
  },
  "N670LK": {
    "no_availability_all_day": false,
    "conflict_tijden": "17:48–18:53"
  },
  "N746KJ": {
    "no_availability_all_day": false,
    "conflict_tijden": "17:48–22:00"
  },
  "N806JV": {
    "no_availability_all_day": false,
    "conflict_tijden": "18:30–00:00"
  },
  "N807JV": {
    "no_availability_all_day": false,
    "conflict_tijden": ""
  },
  "N869KH": {
    "no_availability_all_day": true,
    "conflict_tijden": "17:48–11:48"
  },
  "N880RN": {
    "no_availability_all_day": true,
    "conflict_tijden": "17:48–11:48"
  },
  "P042SK": {
    "no_availability_all_day": false,
    "conflict_tijden": ""
  },
  "P146TT": {
    "no_availability_all_day": false,
    "conflict_tijden": ""
  },
  "P234VS": {
    "no_availability_all_day": false,
    "conflict_tijden": ""
  },
  "P252JZ": {
    "no_availability_all_day": false,
    "conflict_tijden": "17:48–21:00"
  },
  "P269JZ": {
    "no_availability_all_day": true,
    "conflict_tijden": "17:48–11:48"
  },
  "P270JZ": {
    "no_availability_all_day": false,
    "conflict_tijden": "10:00–11:48"
  },
  "P323GR": {
    "no_availability_all_day": false,
    "conflict_tijden": "17:48–23:30"
  },
  "P619VV": {
    "no_availability_all_day": false,
    "conflict_tijden": ""
  },
  "P623VV": {
    "no_availability_all_day": false,
    "conflict_tijden": ""
  },
  "P663XP": {
    "no_availability_all_day": true,
    "conflict_tijden": "17:48–11:48"
  },
  "P666ZP": {
    "no_availability_all_day": false,
    "conflict_tijden": "06:45–11:48"
  },
  "P672FJ": {
    "no_availability_all_day": true,
    "conflict_tijden": "17:48–11:48"
  },
  "P788TV": {
    "no_availability_all_day": false,
    "conflict_tijden": "10:30–11:48"
  },
  "P794KN": {
    "no_availability_all_day": false,
    "conflict_tijden": ""
  },
  "P797KN": {
    "no_availability_all_day": true,
    "conflict_tijden": "17:48–11:48"
  },
  "P798KN": {
    "no_availability_all_day": false,
    "conflict_tijden": ""
  },
  "P887VH": {
    "no_availability_all_day": false,
    "conflict_tijden": ""
  },
  "P991TK": {
    "no_availability_all_day": true,
    "conflict_tijden": "17:48–11:48"
  },
  "R019HK": {
    "no_availability_all_day": false,
    "conflict_tijden": ""
  },
  "R241BD": {
    "no_availability_all_day": false,
    "conflict_tijden": "17:48–19:41"
  },
  "R576FP": {
    "no_availability_all_day": true,
    "conflict_tijden": "17:48–11:48"
  },
  "R580FP": {
    "no_availability_all_day": false,
    "conflict_tijden": ""
  },
  "R793TJ": {
    "no_availability_all_day": true,
    "conflict_tijden": "17:48–11:48"
  },
  "R797JB": {
    "no_availability_all_day": false,
    "conflict_tijden": ""
  },
  "R967JS": {
    "no_availability_all_day": true,
    "conflict_tijden": "17:48–11:48"
  },
  "R976JS": {
    "no_availability_all_day": false,
    "conflict_tijden": "07:30–11:48"
  },
  "S008KK": {
    "no_availability_all_day": false,
    "conflict_tijden": ""
  },
  "S127GZ": {
    "no_availability_all_day": false,
    "conflict_tijden": "18:30–00:15"
  },
  "S135GZ": {
    "no_availability_all_day": true,
    "conflict_tijden": "17:48–11:48"
  },
  "S259SH": {
    "no_availability_all_day": false,
    "conflict_tijden": ""
  },
  "S265SH": {
    "no_availability_all_day": false,
    "conflict_tijden": ""
  },
  "S342BT": {
    "no_availability_all_day": false,
    "conflict_tijden": ""
  },
  "S343BT": {
    "no_availability_all_day": false,
    "conflict_tijden": ""
  },
  "S346BT": {
    "no_availability_all_day": false,
    "conflict_tijden": ""
  },
  "S357BT": {
    "no_availability_all_day": false,
    "conflict_tijden": ""
  },
  "S366BT": {
    "no_availability_all_day": true,
    "conflict_tijden": "17:48–11:48"
  },
  "S681TS": {
    "no_availability_all_day": true,
    "conflict_tijden": "17:48–11:48"
  },
  "S696TS": {
    "no_availability_all_day": false,
    "conflict_tijden": ""
  },
  "T137DJ": {
    "no_availability_all_day": true,
    "conflict_tijden": "17:48–11:48"
  },
  "T140DJ": {
    "no_availability_all_day": false,
    "conflict_tijden": ""
  },
  "T232JG": {
    "no_availability_all_day": true,
    "conflict_tijden": "17:48–11:48"
  },
  "T237HV": {
    "no_availability_all_day": false,
    "conflict_tijden": ""
  },
  "T237JG": {
    "no_availability_all_day": false,
    "conflict_tijden": "07:00–11:48"
  },
  "T416KX": {
    "no_availability_all_day": false,
    "conflict_tijden": "17:48–19:13, 00:15–02:45"
  },
  "T458JJ": {
    "no_availability_all_day": false,
    "conflict_tijden": ""
  },
  "T460KG": {
    "no_availability_all_day": true,
    "conflict_tijden": "17:48–11:48"
  },
  "T462JJ": {
    "no_availability_all_day": false,
    "conflict_tijden": "17:48–22:00"
  },
  "T560KK": {
    "no_availability_all_day": true,
    "conflict_tijden": "17:48–11:48"
  },
  "T619JK": {
    "no_availability_all_day": false,
    "conflict_tijden": ""
  },
  "T694JT": {
    "no_availability_all_day": false,
    "conflict_tijden": ""
  },
  "T803ZN": {
    "no_availability_all_day": false,
    "conflict_tijden": ""
  },
  "T805ZN": {
    "no_availability_all_day": true,
    "conflict_tijden": "17:48–11:48"
  },
  "T806ZN": {
    "no_availability_all_day": false,
    "conflict_tijden": "07:00–11:48"
  },
  "T820PB": {
    "no_availability_all_day": false,
    "conflict_tijden": ""
  },
  "T829ZN": {
    "no_availability_all_day": false,
    "conflict_tijden": "17:48–22:00"
  },
  "T834ZN": {
    "no_availability_all_day": true,
    "conflict_tijden": "17:48–11:48"
  },
  "T839ZN": {
    "no_availability_all_day": false,
    "conflict_tijden": "17:48–22:00, 11:15–11:48"
  },
  "T861DH": {
    "no_availability_all_day": false,
    "conflict_tijden": ""
  },
  "T861KN": {
    "no_availability_all_day": true,
    "conflict_tijden": "17:48–11:48"
  },
  "T865KN": {
    "no_availability_all_day": true,
    "conflict_tijden": "17:48–11:48"
  },
  "T872BZ": {
    "no_availability_all_day": false,
    "conflict_tijden": ""
  },
  "T882BZ": {
    "no_availability_all_day": false,
    "conflict_tijden": ""
  },
  "T883BZ": {
    "no_availability_all_day": false,
    "conflict_tijden": ""
  },
  "T935DH": {
    "no_availability_all_day": true,
    "conflict_tijden": "17:48–11:48"
  },
  "T963DH": {
    "no_availability_all_day": false,
    "conflict_tijden": "19:00–21:30"
  }
}