{
  "HHV42T": {
    "no_availability_all_day": false,
    "conflict_tijden": "09:32–19:00"
  },
  "HHV44T": {
    "no_availability_all_day": false,
    "conflict_tijden": "17:45–22:45"
  },
  "HHV45T": {
    "no_availability_all_day": false,
    "conflict_tijden": ""
  },
  "HHV50T": {
    "no_availability_all_day": false,
    "conflict_tijden": "09:32–14:30"
  },
  "HHV53T": {
    "no_availability_all_day": false,
    "conflict_tijden": "18:00–00:00"
  },
  "HHV54T": {
    "no_availability_all_day": true,
    "conflict_tijden": "09:32–03:32"
  },
  "HHV67T": {
    "no_availability_all_day": false,
    "conflict_tijden": "10:30–12:30, 19:30–23:30"
  },
  "HJD82F": {
    "no_availability_all_day": false,
    "conflict_tijden": ""
  },
  "HJG70F": {
    "no_availability_all_day": false,
    "conflict_tijden": ""
  },
  "J600HR": {
    "no_availability_all_day": true,
    "conflict_tijden": "09:32–03:32"
  },
  "J608HR": {
    "no_availability_all_day": false,
    "conflict_tijden": ""
  },
  "J610HR": {
    "no_availability_all_day": false,
    "conflict_tijden": "09:32–12:15"
  },
  "J613HR": {
    "no_availability_all_day": false,
    "conflict_tijden": ""
  },
  "JPD22G": {
    "no_availability_all_day": true,
    "conflict_tijden": "09:32–03:32"
  },
  "JPD26G": {
    "no_availability_all_day": false,
    "conflict_tijden": ""
  },
  "JPD40G": {
    "no_availability_all_day": false,
    "conflict_tijden": "09:32–18:00"
  },
  "JPD48G": {
    "no_availability_all_day": false,
    "conflict_tijden": "19:00–00:00"
  },
  "JPD51G": {
    "no_availability_all_day": true,
    "conflict_tijden": "09:32–03:32"
  },
  "JPD55G": {
    "no_availability_all_day": false,
    "conflict_tijden": ""
  },
  "JPD65G": {
    "no_availability_all_day": false,
    "conflict_tijden": "09:32–19:45"
  },
  "JPD69G": {
    "no_availability_all_day": false,
    "conflict_tijden": "09:32–15:00"
  },
  "JPD74G": {
    "no_availability_all_day": false,
    "conflict_tijden": ""
  },
  "JPD81G": {
    "no_availability_all_day": false,
    "conflict_tijden": "12:30–19:00"
  },
  "JPD90G": {
    "no_availability_all_day": true,
    "conflict_tijden": "09:32–03:32"
  },
  "JRH24T": {
    "no_availability_all_day": true,
    "conflict_tijden": "09:32–03:32"
  },
  "JRH31T": {
    "no_availability_all_day": false,
    "conflict_tijden": ""
  },
  "JRH46T": {
    "no_availability_all_day": false,
    "conflict_tijden": ""
  },
  "JRH50T": {
    "no_availability_all_day": false,
    "conflict_tijden": "09:32–11:32"
  },
  "JRH58T": {
    "no_availability_all_day": false,
    "conflict_tijden": "18:00–22:00"
  },
  "JRH59T": {
    "no_availability_all_day": false,
    "conflict_tijden": "09:32–18:30"
  },
  "JRH63T": {
    "no_availability_all_day": true,
    "conflict_tijden": "09:32–03:32"
  },
  "JRH68T": {
    "no_availability_all_day": false,
    "conflict_tijden": "09:32–17:00"
  },
  "JRH74T": {
    "no_availability_all_day": true,
    "conflict_tijden": "09:32–03:32"
  },
  "JRH85T": {
    "no_availability_all_day": false,
    "conflict_tijden": ""
  },
  "K018JT": {
    "no_availability_all_day": true,
    "conflict_tijden": "09:32–03:32"
  },
  "K052FN": {
    "no_availability_all_day": false,
    "conflict_tijden": ""
  },
  "K218DF": {
    "no_availability_all_day": false,
    "conflict_tijden": ""
  },
  "K219DF": {
    "no_availability_all_day": false,
    "conflict_tijden": ""
  },
  "K331XD": {
    "no_availability_all_day": false,
    "conflict_tijden": "09:32–21:00"
  },
  "K398NP": {
    "no_availability_all_day": false,
    "conflict_tijden": "10:00–13:00"
  },
  "K405NP": {
    "no_availability_all_day": false,
    "conflict_tijden": "09:32–17:00"
  },
  "K426NP": {
    "no_availability_all_day": false,
    "conflict_tijden": "10:22–03:32"
  },
  "K447NP": {
    "no_availability_all_day": false,
    "conflict_tijden": "12:00–18:00"
  },
  "K454NP": {
    "no_availability_all_day": true,
    "conflict_tijden": "09:32–03:32"
  },
  "K459NP": {
    "no_availability_all_day": false,
    "conflict_tijden": ""
  },
  "K491GV": {
    "no_availability_all_day": true,
    "conflict_tijden": "09:32–03:32"
  },
  "K502FN": {
    "no_availability_all_day": true,
    "conflict_tijden": "09:32–03:32"
  },
  "K525JK": {
    "no_availability_all_day": true,
    "conflict_tijden": "09:32–03:32"
  },
  "K536JK": {
    "no_availability_all_day": false,
    "conflict_tijden": "09:32–20:00"
  },
  "K553JK": {
    "no_availability_all_day": false,
    "conflict_tijden": "12:15–21:45"
  },
  "K557FN": {
    "no_availability_all_day": false,
    "conflict_tijden": ""
  },
  "K558FN": {
    "no_availability_all_day": false,
    "conflict_tijden": "10:30–19:30"
  },
  "K648JH": {
    "no_availability_all_day": false,
    "conflict_tijden": ""
  },
  "K649SR": {
    "no_availability_all_day": true,
    "conflict_tijden": "09:32–03:32"
  },
  "K650JH": {
    "no_availability_all_day": false,
    "conflict_tijden": ""
  },
  "K651JH": {
    "no_availability_all_day": false,
    "conflict_tijden": ""
  },
  "K656FF": {
    "no_availability_all_day": false,
    "conflict_tijden": "09:32–00:00"
  },
  "K657JH": {
    "no_availability_all_day": true,
    "conflict_tijden": "09:32–03:32"
  },
  "K745JH": {
    "no_availability_all_day": false,
    "conflict_tijden": ""
  },
  "K782NR": {
    "no_availability_all_day": true,
    "conflict_tijden": "09:32–03:32"
  },
  "K818JH": {
    "no_availability_all_day": false,
    "conflict_tijden": ""
  },
  "K971JS": {
    "no_availability_all_day": false,
    "conflict_tijden": "09:32–15:45"
  },
  "K981JS": {
    "no_availability_all_day": false,
    "conflict_tijden": "09:32–12:00"
  },
  "K996JS": {
    "no_availability_all_day": false,
    "conflict_tijden": ""
  },
  "L031GG": {
    "no_availability_all_day": false,
    "conflict_tijden": "09:32–20:30"
  },
  "L034GG": {
    "no_availability_all_day": false,
    "conflict_tijden": ""
  },
  "L039GG": {
    "no_availability_all_day": true,
    "conflict_tijden": "09:32–03:32"
  },
  "L041GG": {
    "no_availability_all_day": true,
    "conflict_tijden": "09:32–03:32"
  },
  "L056GG": {
    "no_availability_all_day": false,
    "conflict_tijden": ""
  },
  "L059ZR": {
    "no_availability_all_day": false,
    "conflict_tijden": "09:32–00:00"
  },
  "L085HG": {
    "no_availability_all_day": false,
    "conflict_tijden": ""
  },
  "L088HG": {
    "no_availability_all_day": false,
    "conflict_tijden": "15:00–20:30"
  },
  "L094HG": {
    "no_availability_all_day": false,
    "conflict_tijden": "09:32–15:00"
  },
  "L095HG": {
    "no_availability_all_day": false,
    "conflict_tijden": "10:00–16:00"
  },
  "L101ZP": {
    "no_availability_all_day": false,
    "conflict_tijden": ""
  },
  "L103ZP": {
    "no_availability_all_day": false,
    "conflict_tijden": "13:45–17:00"
  },
  "L104HG": {
    "no_availability_all_day": false,
    "conflict_tijden": ""
  },
  "L106ZP": {
    "no_availability_all_day": false,
    "conflict_tijden": "10:15–14:00"
  },
  "L247NJ": {
    "no_availability_all_day": false,
    "conflict_tijden": ""
  },
  "L251NJ": {
    "no_availability_all_day": false,
    "conflict_tijden": ""
  },
  "L318XB": {
    "no_availability_all_day": false,
    "conflict_tijden": "11:30–16:30"
  },
  "L375ST": {
    "no_availability_all_day": false,
    "conflict_tijden": ""
  },
  "L376ST": {
    "no_availability_all_day": false,
    "conflict_tijden": ""
  },
  "L513BP": {
    "no_availability_all_day": false,
    "conflict_tijden": ""
  },
  "L538BK": {
    "no_availability_all_day": false,
    "conflict_tijden": ""
  },
  "L566PV": {
    "no_availability_all_day": true,
    "conflict_tijden": "09:32–03:32"
  },
  "L576PV": {
    "no_availability_all_day": false,
    "conflict_tijden": "14:45–23:15"
  },
  "L588PV": {
    "no_availability_all_day": false,
    "conflict_tijden": "17:45–20:00"
  },
  "L589PV": {
    "no_availability_all_day": false,
    "conflict_tijden": ""
  },
  "L626KP": {
    "no_availability_all_day": false,
    "conflict_tijden": ""
  },
  "L632KP": {
    "no_availability_all_day": false,
    "conflict_tijden": ""
  },
  "L633KP": {
    "no_availability_all_day": true,
    "conflict_tijden": "09:32–03:32"
  },
  "L638KP": {
    "no_availability_all_day": false,
    "conflict_tijden": ""
  },
  "L643KP": {
    "no_availability_all_day": true,
    "conflict_tijden": "09:32–03:32"
  },
  "L644KP": {
    "no_availability_all_day": false,
    "conflict_tijden": ""
  },
  "L664FV": {
    "no_availability_all_day": false,
    "conflict_tijden": ""
  },
  "L665GR": {
    "no_availability_all_day": false,
    "conflict_tijden": "14:30–19:00"
  },
  "L697KP": {
    "no_availability_all_day": false,
    "conflict_tijden": ""
  },
  "L835NR": {
    "no_availability_all_day": false,
    "conflict_tijden": "13:30–20:00"
  },
  "L865GX": {
    "no_availability_all_day": false,
    "conflict_tijden": "09:32–14:15"
  },
  "L882NR": {
    "no_availability_all_day": true,
    "conflict_tijden": "09:32–03:32"
  },
  "L883NR": {
    "no_availability_all_day": false,
    "conflict_tijden": ""
  },
  "L979NL": {
    "no_availability_all_day": false,
    "conflict_tijden": ""
  },
  "N061JD": {
    "no_availability_all_day": false,
    "conflict_tijden": ""
  },
  "N089KV": {
    "no_availability_all_day": false,
    "conflict_tijden": ""
  },
  "N097BR": {
    "no_availability_all_day": false,
    "conflict_tijden": ""
  },
  "N098BR": {
    "no_availability_all_day": false,
    "conflict_tijden": ""
  },
  "N141RD": {
    "no_availability_all_day": false,
    "conflict_tijden": "13:45–15:45"
  },
  "N145RZ": {
    "no_availability_all_day": false,
    "conflict_tijden": ""
  },
  "N147RD": {
    "no_availability_all_day": false,
    "conflict_tijden": ""
  },
  "N155RD": {
    "no_availability_all_day": true,
    "conflict_tijden": "09:32–03:32"
  },
  "N157RD": {
    "no_availability_all_day": false,
    "conflict_tijden": "09:32–14:00"
  },
  "N159RZ": {
    "no_availability_all_day": false,
    "conflict_tijden": "09:32–19:30"
  },
  "N160RD": {
    "no_availability_all_day": false,
    "conflict_tijden": ""
  },
  "N187RD": {
    "no_availability_all_day": true,
    "conflict_tijden": "09:32–03:32"
  },
  "N195HV": {
    "no_availability_all_day": true,
    "conflict_tijden": "09:32–03:32"
  },
  "N200BH": {
    "no_availability_all_day": false,
    "conflict_tijden": ""
  },
  "N204HV": {
    "no_availability_all_day": false,
    "conflict_tijden": ""
  },
  "N217HV": {
    "no_availability_all_day": false,
    "conflict_tijden": "09:32–18:30"
  },
  "N220DL": {
    "no_availability_all_day": false,
    "conflict_tijden": "09:32–11:01"
  },
  "N225PF": {
    "no_availability_all_day": false,
    "conflict_tijden": "09:32–19:00"
  },
  "N236PF": {
    "no_availability_all_day": false,
    "conflict_tijden": ""
  },
  "N243PF": {
    "no_availability_all_day": false,
    "conflict_tijden": ""
  },
  "N248VT": {
    "no_availability_all_day": false,
    "conflict_tijden": ""
  },
  "N250VT": {
    "no_availability_all_day": true,
    "conflict_tijden": "09:32–03:32"
  },
  "N251VT": {
    "no_availability_all_day": true,
    "conflict_tijden": "09:32–03:32"
  },
  "N274KS": {
    "no_availability_all_day": false,
    "conflict_tijden": "09:32–19:30"
  },
  "N292PS": {
    "no_availability_all_day": true,
    "conflict_tijden": "09:32–03:32"
  },
  "N298VT": {
    "no_availability_all_day": true,
    "conflict_tijden": "09:32–03:32"
  },
  "N303VT": {
    "no_availability_all_day": false,
    "conflict_tijden": ""
  },
  "N308PS": {
    "no_availability_all_day": false,
    "conflict_tijden": "10:00–15:00"
  },
  "N317PS": {
    "no_availability_all_day": false,
    "conflict_tijden": "10:15–17:00"
  },
  "N318VT": {
    "no_availability_all_day": false,
    "conflict_tijden": "09:32–18:30"
  },
  "N344RG": {
    "no_availability_all_day": true,
    "conflict_tijden": "09:32–03:32"
  },
  "N344SF": {
    "no_availability_all_day": false,
    "conflict_tijden": ""
  },
  "N360VT": {
    "no_availability_all_day": false,
    "conflict_tijden": ""
  },
  "N363RG": {
    "no_availability_all_day": false,
    "conflict_tijden": "09:32–11:24"
  },
  "N365RG": {
    "no_availability_all_day": false,
    "conflict_tijden": ""
  },
  "N366RG": {
    "no_availability_all_day": false,
    "conflict_tijden": ""
  },
  "N372RG": {
    "no_availability_all_day": false,
    "conflict_tijden": ""
  },
  "N379RG": {
    "no_availability_all_day": false,
    "conflict_tijden": "09:32–17:00"
  },
  "N387VT": {
    "no_availability_all_day": false,
    "conflict_tijden": "09:32–10:30"
  },
  "N397LD": {
    "no_availability_all_day": false,
    "conflict_tijden": ""
  },
  "N404LD": {
    "no_availability_all_day": true,
    "conflict_tijden": "09:32–03:32"
  },
  "N406LD": {
    "no_availability_all_day": false,
    "conflict_tijden": ""
  },
  "N407LD": {
    "no_availability_all_day": true,
    "conflict_tijden": "09:32–03:32"
  },
  "N408LD": {
    "no_availability_all_day": false,
    "conflict_tijden": ""
  },
  "N416BF": {
    "no_availability_all_day": false,
    "conflict_tijden": "09:32–12:00"
  },
  "N420VT": {
    "no_availability_all_day": false,
    "conflict_tijden": ""
  },
  "N438VT": {
    "no_availability_all_day": false,
    "conflict_tijden": ""
  },
  "N447VT": {
    "no_availability_all_day": false,
    "conflict_tijden": "09:32–16:15"
  },
  "N453VT": {
    "no_availability_all_day": false,
    "conflict_tijden": ""
  },
  "N465NR": {
    "no_availability_all_day": false,
    "conflict_tijden": "09:32–18:00"
  },
  "N480NR": {
    "no_availability_all_day": false,
    "conflict_tijden": "13:45–15:45"
  },
  "N489TF": {
    "no_availability_all_day": false,
    "conflict_tijden": ""
  },
  "N491NR": {
    "no_availability_all_day": false,
    "conflict_tijden": "14:00–16:30"
  },
  "N494TF": {
    "no_availability_all_day": true,
    "conflict_tijden": "09:32–03:32"
  },
  "N519DN": {
    "no_availability_all_day": true,
    "conflict_tijden": "09:32–03:32"
  },
  "N533VX": {
    "no_availability_all_day": false,
    "conflict_tijden": ""
  },
  "N536VX": {
    "no_availability_all_day": false,
    "conflict_tijden": "19:15–21:15"
  },
  "N560VX": {
    "no_availability_all_day": true,
    "conflict_tijden": "09:32–03:32"
  },
  "N565VX": {
    "no_availability_all_day": false,
    "conflict_tijden": "09:32–09:46"
  },
  "N568VX": {
    "no_availability_all_day": false,
    "conflict_tijden": "14:30–18:00"
  },
  "N574VX": {
    "no_availability_all_day": false,
    "conflict_tijden": ""
  },
  "N576VX": {
    "no_availability_all_day": false,
    "conflict_tijden": ""
  },
  "N584NL": {
    "no_availability_all_day": true,
    "conflict_tijden": "09:32–03:32"
  },
  "N585NL": {
    "no_availability_all_day": false,
    "conflict_tijden": "09:32–13:30"
  },
  "N587NL": {
    "no_availability_all_day": false,
    "conflict_tijden": ""
  },
  "N596NL": {
    "no_availability_all_day": false,
    "conflict_tijden": ""
  },
  "N602PD": {
    "no_availability_all_day": false,
    "conflict_tijden": "09:32–12:30"
  },
  "N607NV": {
    "no_availability_all_day": false,
    "conflict_tijden": ""
  },
  "N609PD": {
    "no_availability_all_day": true,
    "conflict_tijden": "09:32–03:32"
  },
  "N637NV": {
    "no_availability_all_day": false,
    "conflict_tijden": "09:32–12:00"
  },
  "N638NV": {
    "no_availability_all_day": false,
    "conflict_tijden": ""
  },
  "N647NV": {
    "no_availability_all_day": false,
    "conflict_tijden": "09:32–17:30"
  },
  "N658KK": {
    "no_availability_all_day": false,
    "conflict_tijden": "13:30–19:00"
  },
  "N664LK": {
    "no_availability_all_day": false,
    "conflict_tijden": ""
  },
  "N670LK": {
    "no_availability_all_day": false,
    "conflict_tijden": "09:32–15:00"
  },
  "N746KJ": {
    "no_availability_all_day": false,
    "conflict_tijden": "10:30–13:30"
  },
  "N806JV": {
    "no_availability_all_day": false,
    "conflict_tijden": "10:30–14:00"
  },
  "N807JV": {
    "no_availability_all_day": false,
    "conflict_tijden": ""
  },
  "N813JV": {
    "no_availability_all_day": false,
    "conflict_tijden": ""
  },
  "N822JV": {
    "no_availability_all_day": false,
    "conflict_tijden": "12:15–18:30"
  },
  "N824JV": {
    "no_availability_all_day": false,
    "conflict_tijden": ""
  },
  "N830JV": {
    "no_availability_all_day": false,
    "conflict_tijden": ""
  },
  "N831JV": {
    "no_availability_all_day": false,
    "conflict_tijden": "09:32–20:00"
  },
  "N866RN": {
    "no_availability_all_day": true,
    "conflict_tijden": "09:32–03:32"
  },
  "N869KH": {
    "no_availability_all_day": false,
    "conflict_tijden": "09:32–00:00"
  },
  "N880RN": {
    "no_availability_all_day": true,
    "conflict_tijden": "09:32–03:32"
  },
  "N967DH": {
    "no_availability_all_day": true,
    "conflict_tijden": "09:32–03:32"
  },
  "N974DH": {
    "no_availability_all_day": false,
    "conflict_tijden": ""
  },
  "P042SK": {
    "no_availability_all_day": false,
    "conflict_tijden": ""
  },
  "P168RT": {
    "no_availability_all_day": false,
    "conflict_tijden": "09:32–17:00"
  },
  "P234VS": {
    "no_availability_all_day": false,
    "conflict_tijden": ""
  },
  "P235VS": {
    "no_availability_all_day": false,
    "conflict_tijden": "19:45–03:32"
  },
  "P252JZ": {
    "no_availability_all_day": false,
    "conflict_tijden": "11:15–18:00"
  },
  "P269JZ": {
    "no_availability_all_day": true,
    "conflict_tijden": "09:32–03:32"
  },
  "P270JZ": {
    "no_availability_all_day": false,
    "conflict_tijden": "09:32–13:00"
  },
  "P323GR": {
    "no_availability_all_day": false,
    "conflict_tijden": ""
  },
  "P418LP": {
    "no_availability_all_day": false,
    "conflict_tijden": "09:32–19:30"
  },
  "P430XS": {
    "no_availability_all_day": false,
    "conflict_tijden": "09:32–10:34, 12:00–20:15"
  },
  "P498VB": {
    "no_availability_all_day": true,
    "conflict_tijden": "09:32–03:32"
  },
  "P619VV": {
    "no_availability_all_day": false,
    "conflict_tijden": ""
  },
  "P623VV": {
    "no_availability_all_day": false,
    "conflict_tijden": ""
  },
  "P663XP": {
    "no_availability_all_day": true,
    "conflict_tijden": "09:32–03:32"
  },
  "P666ZP": {
    "no_availability_all_day": true,
    "conflict_tijden": "09:32–03:32"
  },
  "P672FJ": {
    "no_availability_all_day": true,
    "conflict_tijden": "09:32–03:32"
  },
  "P788TV": {
    "no_availability_all_day": false,
    "conflict_tijden": ""
  },
  "P794KN": {
    "no_availability_all_day": false,
    "conflict_tijden": ""
  },
  "P797KN": {
    "no_availability_all_day": false,
    "conflict_tijden": ""
  },
  "P798KN": {
    "no_availability_all_day": false,
    "conflict_tijden": ""
  },
  "P804ZL": {
    "no_availability_all_day": false,
    "conflict_tijden": ""
  },
  "P887VH": {
    "no_availability_all_day": false,
    "conflict_tijden": ""
  },
  "P991TK": {
    "no_availability_all_day": true,
    "conflict_tijden": "09:32–03:32"
  },
  "R019HK": {
    "no_availability_all_day": false,
    "conflict_tijden": ""
  },
  "R020HG": {
    "no_availability_all_day": false,
    "conflict_tijden": ""
  },
  "R576FP": {
    "no_availability_all_day": true,
    "conflict_tijden": "09:32–03:32"
  },
  "R580FP": {
    "no_availability_all_day": false,
    "conflict_tijden": ""
  },
  "R793TJ": {
    "no_availability_all_day": true,
    "conflict_tijden": "09:32–03:32"
  },
  "R795JB": {
    "no_availability_all_day": false,
    "conflict_tijden": ""
  },
  "R967JS": {
    "no_availability_all_day": true,
    "conflict_tijden": "09:32–03:32"
  },
  "R976JS": {
    "no_availability_all_day": false,
    "conflict_tijden": ""
  },
  "S008KK": {
    "no_availability_all_day": false,
    "conflict_tijden": "09:32–19:30"
  },
  "S009KK": {
    "no_availability_all_day": true,
    "conflict_tijden": "09:32–03:32"
  },
  "S127GZ": {
    "no_availability_all_day": false,
    "conflict_tijden": ""
  },
  "S135GZ": {
    "no_availability_all_day": false,
    "conflict_tijden": ""
  },
  "S250SH": {
    "no_availability_all_day": true,
    "conflict_tijden": "09:32–03:32"
  },
  "S259SH": {
    "no_availability_all_day": false,
    "conflict_tijden": ""
  },
  "S342BT": {
    "no_availability_all_day": false,
    "conflict_tijden": "09:32–10:53"
  },
  "S343BT": {
    "no_availability_all_day": false,
    "conflict_tijden": ""
  },
  "S345BT": {
    "no_availability_all_day": false,
    "conflict_tijden": "12:00–15:00"
  },
  "S346BT": {
    "no_availability_all_day": false,
    "conflict_tijden": "09:32–18:30"
  },
  "S357BT": {
    "no_availability_all_day": false,
    "conflict_tijden": "13:00–18:00"
  },
  "S366BT": {
    "no_availability_all_day": true,
    "conflict_tijden": "09:32–03:32"
  },
  "S681TS": {
    "no_availability_all_day": false,
    "conflict_tijden": "09:32–10:54"
  },
  "S696TS": {
    "no_availability_all_day": false,
    "conflict_tijden": ""
  },
  "S705TS": {
    "no_availability_all_day": false,
    "conflict_tijden": ""
  },
  "T137DJ": {
    "no_availability_all_day": true,
    "conflict_tijden": "09:32–03:32"
  },
  "T232JG": {
    "no_availability_all_day": true,
    "conflict_tijden": "09:32–03:32"
  },
  "T237JG": {
    "no_availability_all_day": true,
    "conflict_tijden": "09:32–03:32"
  },
  "T458JJ": {
    "no_availability_all_day": false,
    "conflict_tijden": "12:00–15:00"
  },
  "T460KG": {
    "no_availability_all_day": false,
    "conflict_tijden": ""
  },
  "T462JJ": {
    "no_availability_all_day": false,
    "conflict_tijden": ""
  },
  "T560KK": {
    "no_availability_all_day": true,
    "conflict_tijden": "09:32–03:32"
  },
  "T618JK": {
    "no_availability_all_day": false,
    "conflict_tijden": ""
  },
  "T619JK": {
    "no_availability_all_day": false,
    "conflict_tijden": ""
  },
  "T674JK": {
    "no_availability_all_day": false,
    "conflict_tijden": ""
  },
  "T694JT": {
    "no_availability_all_day": false,
    "conflict_tijden": "12:00–18:30"
  },
  "T795ZN": {
    "no_availability_all_day": false,
    "conflict_tijden": "10:00–17:15"
  },
  "T803ZN": {
    "no_availability_all_day": false,
    "conflict_tijden": ""
  },
  "T805ZN": {
    "no_availability_all_day": true,
    "conflict_tijden": "09:32–03:32"
  },
  "T806ZN": {
    "no_availability_all_day": false,
    "conflict_tijden": "09:32–12:30"
  },
  "T820PB": {
    "no_availability_all_day": false,
    "conflict_tijden": "10:30–14:00, 20:15–23:00"
  },
  "T829ZN": {
    "no_availability_all_day": false,
    "conflict_tijden": ""
  },
  "T839ZN": {
    "no_availability_all_day": false,
    "conflict_tijden": "16:00–22:00"
  },
  "T852DH": {
    "no_availability_all_day": false,
    "conflict_tijden": ""
  },
  "T861DH": {
    "no_availability_all_day": false,
    "conflict_tijden": ""
  },
  "T861KN": {
    "no_availability_all_day": false,
    "conflict_tijden": "09:32–00:00"
  },
  "T865KN": {
    "no_availability_all_day": true,
    "conflict_tijden": "09:32–03:32"
  },
  "T867KN": {
    "no_availability_all_day": false,
    "conflict_tijden": ""
  },
  "T872BZ": {
    "no_availability_all_day": false,
    "conflict_tijden": "18:00–00:30"
  },
  "T872DH": {
    "no_availability_all_day": false,
    "conflict_tijden": "12:45–16:30"
  },
  "T882BZ": {
    "no_availability_all_day": false,
    "conflict_tijden": ""
  },
  "T883BZ": {
    "no_availability_all_day": false,
    "conflict_tijden": ""
  },
  "T935DH": {
    "no_availability_all_day": true,
    "conflict_tijden": "09:32–03:32"
  },
  "T963DH": {
    "no_availability_all_day": true,
    "conflict_tijden": "09:32–03:32"
  }
}