{
  "G453XX": {
    "no_availability_all_day": false,
    "conflict_tijden": "17:34–19:00, 08:00–11:34"
  },
  "HHV31T": {
    "no_availability_all_day": false,
    "conflict_tijden": ""
  },
  "HHV36T": {
    "no_availability_all_day": false,
    "conflict_tijden": ""
  },
  "HHV66T": {
    "no_availability_all_day": true,
    "conflict_tijden": "17:34–11:34"
  },
  "HHV68T": {
    "no_availability_all_day": true,
    "conflict_tijden": "17:34–11:34"
  },
  "HHV72T": {
    "no_availability_all_day": true,
    "conflict_tijden": "17:34–11:34"
  },
  "J098JV": {
    "no_availability_all_day": false,
    "conflict_tijden": "17:34–22:30, 10:30–11:34"
  },
  "J600HR": {
    "no_availability_all_day": true,
    "conflict_tijden": "17:34–11:34"
  },
  "J614HR": {
    "no_availability_all_day": false,
    "conflict_tijden": "17:34–19:21, 06:00–11:34"
  },
  "J649VB": {
    "no_availability_all_day": false,
    "conflict_tijden": "17:34–20:00"
  },
  "J836JH": {
    "no_availability_all_day": false,
    "conflict_tijden": "08:15–11:34"
  },
  "JPD21G": {
    "no_availability_all_day": false,
    "conflict_tijden": ""
  },
  "JPD22G": {
    "no_availability_all_day": false,
    "conflict_tijden": ""
  },
  "JPD24G": {
    "no_availability_all_day": false,
    "conflict_tijden": ""
  },
  "JPD30G": {
    "no_availability_all_day": false,
    "conflict_tijden": ""
  },
  "JPD32G": {
    "no_availability_all_day": false,
    "conflict_tijden": ""
  },
  "JPD34G": {
    "no_availability_all_day": false,
    "conflict_tijden": ""
  },
  "JPD44G": {
    "no_availability_all_day": false,
    "conflict_tijden": ""
  },
  "JPD51G": {
    "no_availability_all_day": true,
    "conflict_tijden": "17:34–11:34"
  },
  "JPD59G": {
    "no_availability_all_day": false,
    "conflict_tijden": ""
  },
  "JPD71G": {
    "no_availability_all_day": false,
    "conflict_tijden": "09:00–11:34"
  },
  "JPD79G": {
    "no_availability_all_day": false,
    "conflict_tijden": "09:00–11:34"
  },
  "JPD80G": {
    "no_availability_all_day": false,
    "conflict_tijden": "07:00–11:34"
  },
  "JPD87G": {
    "no_availability_all_day": false,
    "conflict_tijden": "07:45–11:00"
  },
  "JPD88G": {
    "no_availability_all_day": false,
    "conflict_tijden": "18:15–20:30"
  },
  "JRH21T": {
    "no_availability_all_day": false,
    "conflict_tijden": ""
  },
  "JRH31T": {
    "no_availability_all_day": false,
    "conflict_tijden": ""
  },
  "JRH49T": {
    "no_availability_all_day": false,
    "conflict_tijden": "08:15–11:34"
  },
  "JRH52T": {
    "no_availability_all_day": false,
    "conflict_tijden": ""
  },
  "JRH62T": {
    "no_availability_all_day": false,
    "conflict_tijden": "08:00–11:34"
  },
  "JRH87T": {
    "no_availability_all_day": false,
    "conflict_tijden": "19:00–23:00"
  },
  "K022JT": {
    "no_availability_all_day": true,
    "conflict_tijden": "17:34–11:34"
  },
  "K055FN": {
    "no_availability_all_day": false,
    "conflict_tijden": ""
  },
  "K093ZF": {
    "no_availability_all_day": false,
    "conflict_tijden": ""
  },
  "K222DF": {
    "no_availability_all_day": true,
    "conflict_tijden": "17:34–11:34"
  },
  "K227DF": {
    "no_availability_all_day": false,
    "conflict_tijden": "17:34–19:32, 08:00–11:34"
  },
  "K392NP": {
    "no_availability_all_day": false,
    "conflict_tijden": "17:34–20:45"
  },
  "K393NP": {
    "no_availability_all_day": false,
    "conflict_tijden": ""
  },
  "K395NP": {
    "no_availability_all_day": false,
    "conflict_tijden": "07:00–11:34"
  },
  "K401NP": {
    "no_availability_all_day": false,
    "conflict_tijden": ""
  },
  "K402NP": {
    "no_availability_all_day": true,
    "conflict_tijden": "17:34–11:34"
  },
  "K407NP": {
    "no_availability_all_day": false,
    "conflict_tijden": "17:34–01:45"
  },
  "K430NP": {
    "no_availability_all_day": false,
    "conflict_tijden": ""
  },
  "K452NP": {
    "no_availability_all_day": false,
    "conflict_tijden": "17:34–18:41"
  },
  "K453NP": {
    "no_availability_all_day": false,
    "conflict_tijden": "17:34–21:00"
  },
  "K510JK": {
    "no_availability_all_day": false,
    "conflict_tijden": ""
  },
  "K519FN": {
    "no_availability_all_day": false,
    "conflict_tijden": ""
  },
  "K528JK": {
    "no_availability_all_day": false,
    "conflict_tijden": "17:34–20:45"
  },
  "K535JK": {
    "no_availability_all_day": true,
    "conflict_tijden": "17:34–11:34"
  },
  "K541BZ": {
    "no_availability_all_day": false,
    "conflict_tijden": ""
  },
  "K543JK": {
    "no_availability_all_day": false,
    "conflict_tijden": "19:45–20:45"
  },
  "K592FF": {
    "no_availability_all_day": false,
    "conflict_tijden": ""
  },
  "K644JH": {
    "no_availability_all_day": true,
    "conflict_tijden": "17:34–11:34"
  },
  "K648JH": {
    "no_availability_all_day": false,
    "conflict_tijden": "08:00–11:34"
  },
  "K653JH": {
    "no_availability_all_day": false,
    "conflict_tijden": "08:00–11:34"
  },
  "K656JH": {
    "no_availability_all_day": false,
    "conflict_tijden": "17:34–19:00"
  },
  "K810JH": {
    "no_availability_all_day": false,
    "conflict_tijden": ""
  },
  "K813JH": {
    "no_availability_all_day": false,
    "conflict_tijden": ""
  },
  "K815JH": {
    "no_availability_all_day": false,
    "conflict_tijden": ""
  },
  "K817JH": {
    "no_availability_all_day": false,
    "conflict_tijden": ""
  },
  "K966JS": {
    "no_availability_all_day": false,
    "conflict_tijden": "17:34–19:45, 09:00–11:34"
  },
  "K984JS": {
    "no_availability_all_day": false,
    "conflict_tijden": ""
  },
  "K990JS": {
    "no_availability_all_day": false,
    "conflict_tijden": ""
  },
  "K995JS": {
    "no_availability_all_day": false,
    "conflict_tijden": "17:34–17:44, 10:00–11:34"
  },
  "L035GG": {
    "no_availability_all_day": true,
    "conflict_tijden": "17:34–11:34"
  },
  "L053ZR": {
    "no_availability_all_day": false,
    "conflict_tijden": ""
  },
  "L058ZR": {
    "no_availability_all_day": false,
    "conflict_tijden": ""
  },
  "L064HG": {
    "no_availability_all_day": true,
    "conflict_tijden": "17:34–11:34"
  },
  "L088HG": {
    "no_availability_all_day": false,
    "conflict_tijden": ""
  },
  "L096HG": {
    "no_availability_all_day": false,
    "conflict_tijden": ""
  },
  "L105ZP": {
    "no_availability_all_day": false,
    "conflict_tijden": "10:00–11:34"
  },
  "L107HG": {
    "no_availability_all_day": false,
    "conflict_tijden": ""
  },
  "L108HG": {
    "no_availability_all_day": true,
    "conflict_tijden": "17:34–11:34"
  },
  "L246NJ": {
    "no_availability_all_day": false,
    "conflict_tijden": "08:30–11:34"
  },
  "L251NJ": {
    "no_availability_all_day": false,
    "conflict_tijden": "17:34–18:36"
  },
  "L254NJ": {
    "no_availability_all_day": false,
    "conflict_tijden": ""
  },
  "L372ST": {
    "no_availability_all_day": false,
    "conflict_tijden": "19:00–22:45"
  },
  "L377ST": {
    "no_availability_all_day": false,
    "conflict_tijden": "08:00–11:34"
  },
  "L427TN": {
    "no_availability_all_day": false,
    "conflict_tijden": "17:34–20:30"
  },
  "L514BP": {
    "no_availability_all_day": false,
    "conflict_tijden": "19:00–00:00, 08:00–11:34"
  },
  "L515BP": {
    "no_availability_all_day": false,
    "conflict_tijden": "09:00–11:34"
  },
  "L516LF": {
    "no_availability_all_day": false,
    "conflict_tijden": "17:34–01:00, 08:00–11:34"
  },
  "L517BP": {
    "no_availability_all_day": false,
    "conflict_tijden": "17:34–00:30"
  },
  "L518LF": {
    "no_availability_all_day": false,
    "conflict_tijden": ""
  },
  "L576PV": {
    "no_availability_all_day": false,
    "conflict_tijden": "06:45–11:34"
  },
  "L577PV": {
    "no_availability_all_day": false,
    "conflict_tijden": ""
  },
  "L623KP": {
    "no_availability_all_day": true,
    "conflict_tijden": "17:34–11:34"
  },
  "L627KP": {
    "no_availability_all_day": false,
    "conflict_tijden": "08:00–11:34"
  },
  "L638KP": {
    "no_availability_all_day": false,
    "conflict_tijden": ""
  },
  "L643KP": {
    "no_availability_all_day": true,
    "conflict_tijden": "17:34–11:34"
  },
  "L663GR": {
    "no_availability_all_day": false,
    "conflict_tijden": "17:34–20:30, 07:30–11:34"
  },
  "L699KP": {
    "no_availability_all_day": false,
    "conflict_tijden": "17:34–18:58, 07:00–11:34"
  },
  "L818NR": {
    "no_availability_all_day": true,
    "conflict_tijden": "17:34–11:34"
  },
  "L822NR": {
    "no_availability_all_day": false,
    "conflict_tijden": "17:34–19:24"
  },
  "L832NR": {
    "no_availability_all_day": false,
    "conflict_tijden": "08:15–11:34"
  },
  "L835NR": {
    "no_availability_all_day": false,
    "conflict_tijden": ""
  },
  "L877NR": {
    "no_availability_all_day": false,
    "conflict_tijden": ""
  },
  "L895NV": {
    "no_availability_all_day": false,
    "conflict_tijden": "08:30–11:34"
  },
  "L972NL": {
    "no_availability_all_day": false,
    "conflict_tijden": "10:30–11:34"
  },
  "N062JD": {
    "no_availability_all_day": false,
    "conflict_tijden": ""
  },
  "N129SX": {
    "no_availability_all_day": false,
    "conflict_tijden": "18:00–20:00"
  },
  "N143RD": {
    "no_availability_all_day": false,
    "conflict_tijden": "17:34–00:00"
  },
  "N148RZ": {
    "no_availability_all_day": false,
    "conflict_tijden": "17:34–22:00"
  },
  "N153RZ": {
    "no_availability_all_day": false,
    "conflict_tijden": "17:34–19:19"
  },
  "N161RD": {
    "no_availability_all_day": false,
    "conflict_tijden": "17:34–22:30"
  },
  "N162RD": {
    "no_availability_all_day": false,
    "conflict_tijden": ""
  },
  "N196HV": {
    "no_availability_all_day": false,
    "conflict_tijden": ""
  },
  "N198RD": {
    "no_availability_all_day": false,
    "conflict_tijden": "07:00–11:34"
  },
  "N201HV": {
    "no_availability_all_day": true,
    "conflict_tijden": "17:34–11:34"
  },
  "N206RD": {
    "no_availability_all_day": false,
    "conflict_tijden": "17:34–19:18, 07:00–11:34"
  },
  "N215DL": {
    "no_availability_all_day": false,
    "conflict_tijden": "08:45–11:34"
  },
  "N218DL": {
    "no_availability_all_day": false,
    "conflict_tijden": ""
  },
  "N220HV": {
    "no_availability_all_day": false,
    "conflict_tijden": "17:34–18:59, 11:30–11:34"
  },
  "N221PF": {
    "no_availability_all_day": false,
    "conflict_tijden": "11:00–11:34"
  },
  "N226PF": {
    "no_availability_all_day": false,
    "conflict_tijden": "17:34–00:00"
  },
  "N229PF": {
    "no_availability_all_day": false,
    "conflict_tijden": ""
  },
  "N232PF": {
    "no_availability_all_day": false,
    "conflict_tijden": "17:34–18:39"
  },
  "N233PF": {
    "no_availability_all_day": false,
    "conflict_tijden": ""
  },
  "N238PF": {
    "no_availability_all_day": false,
    "conflict_tijden": "09:45–11:34"
  },
  "N243PF": {
    "no_availability_all_day": false,
    "conflict_tijden": "17:34–21:30"
  },
  "N247PF": {
    "no_availability_all_day": false,
    "conflict_tijden": ""
  },
  "N254VT": {
    "no_availability_all_day": false,
    "conflict_tijden": "10:30–11:34"
  },
  "N268VT": {
    "no_availability_all_day": false,
    "conflict_tijden": ""
  },
  "N269KS": {
    "no_availability_all_day": true,
    "conflict_tijden": "17:34–11:34"
  },
  "N269VT": {
    "no_availability_all_day": true,
    "conflict_tijden": "17:34–11:34"
  },
  "N289PS": {
    "no_availability_all_day": false,
    "conflict_tijden": "17:34–17:42, 09:30–11:34"
  },
  "N296VT": {
    "no_availability_all_day": true,
    "conflict_tijden": "17:34–11:34"
  },
  "N300VT": {
    "no_availability_all_day": false,
    "conflict_tijden": ""
  },
  "N311PS": {
    "no_availability_all_day": false,
    "conflict_tijden": ""
  },
  "N315VT": {
    "no_availability_all_day": false,
    "conflict_tijden": ""
  },
  "N319PS": {
    "no_availability_all_day": false,
    "conflict_tijden": "17:34–23:00"
  },
  "N326SF": {
    "no_availability_all_day": false,
    "conflict_tijden": "06:30–11:34"
  },
  "N338SF": {
    "no_availability_all_day": false,
    "conflict_tijden": ""
  },
  "N340SF": {
    "no_availability_all_day": false,
    "conflict_tijden": ""
  },
  "N340VT": {
    "no_availability_all_day": true,
    "conflict_tijden": "17:34–11:34"
  },
  "N341DP": {
    "no_availability_all_day": false,
    "conflict_tijden": "17:34–18:49"
  },
  "N344RG": {
    "no_availability_all_day": true,
    "conflict_tijden": "17:34–11:34"
  },
  "N347SF": {
    "no_availability_all_day": false,
    "conflict_tijden": ""
  },
  "N350SF": {
    "no_availability_all_day": false,
    "conflict_tijden": "18:15–19:30"
  },
  "N360VT": {
    "no_availability_all_day": false,
    "conflict_tijden": ""
  },
  "N363RG": {
    "no_availability_all_day": false,
    "conflict_tijden": ""
  },
  "N372RG": {
    "no_availability_all_day": false,
    "conflict_tijden": ""
  },
  "N375RG": {
    "no_availability_all_day": false,
    "conflict_tijden": "17:34–23:00"
  },
  "N392LD": {
    "no_availability_all_day": false,
    "conflict_tijden": ""
  },
  "N400LD": {
    "no_availability_all_day": false,
    "conflict_tijden": ""
  },
  "N403VT": {
    "no_availability_all_day": true,
    "conflict_tijden": "17:34–11:34"
  },
  "N404VT": {
    "no_availability_all_day": false,
    "conflict_tijden": ""
  },
  "N408LD": {
    "no_availability_all_day": false,
    "conflict_tijden": ""
  },
  "N413BF": {
    "no_availability_all_day": false,
    "conflict_tijden": ""
  },
  "N414BF": {
    "no_availability_all_day": false,
    "conflict_tijden": "17:34–22:00"
  },
  "N414VT": {
    "no_availability_all_day": false,
    "conflict_tijden": "07:45–11:34"
  },
  "N415BF": {
    "no_availability_all_day": false,
    "conflict_tijden": "08:00–11:34"
  },
  "N420LD": {
    "no_availability_all_day": true,
    "conflict_tijden": "17:34–11:34"
  },
  "N420VT": {
    "no_availability_all_day": false,
    "conflict_tijden": "08:00–11:34"
  },
  "N421VT": {
    "no_availability_all_day": false,
    "conflict_tijden": "17:34–20:15"
  },
  "N438VT": {
    "no_availability_all_day": false,
    "conflict_tijden": "17:34–21:45"
  },
  "N452NR": {
    "no_availability_all_day": false,
    "conflict_tijden": ""
  },
  "N464NR": {
    "no_availability_all_day": false,
    "conflict_tijden": ""
  },
  "N465NR": {
    "no_availability_all_day": false,
    "conflict_tijden": ""
  },
  "N474VT": {
    "no_availability_all_day": false,
    "conflict_tijden": ""
  },
  "N483NR": {
    "no_availability_all_day": false,
    "conflict_tijden": "08:00–11:34"
  },
  "N489TF": {
    "no_availability_all_day": false,
    "conflict_tijden": ""
  },
  "N490NR": {
    "no_availability_all_day": false,
    "conflict_tijden": "17:34–22:00"
  },
  "N491NR": {
    "no_availability_all_day": false,
    "conflict_tijden": ""
  },
  "N494TF": {
    "no_availability_all_day": false,
    "conflict_tijden": ""
  },
  "N522VX": {
    "no_availability_all_day": false,
    "conflict_tijden": ""
  },
  "N523VX": {
    "no_availability_all_day": false,
    "conflict_tijden": "17:34–18:01"
  },
  "N536VX": {
    "no_availability_all_day": false,
    "conflict_tijden": ""
  },
  "N548GD": {
    "no_availability_all_day": false,
    "conflict_tijden": ""
  },
  "N557VX": {
    "no_availability_all_day": false,
    "conflict_tijden": ""
  },
  "N558VX": {
    "no_availability_all_day": false,
    "conflict_tijden": ""
  },
  "N559VX": {
    "no_availability_all_day": false,
    "conflict_tijden": ""
  },
  "N560VX": {
    "no_availability_all_day": true,
    "conflict_tijden": "17:34–11:34"
  },
  "N572VX": {
    "no_availability_all_day": true,
    "conflict_tijden": "17:34–11:34"
  },
  "N573VX": {
    "no_availability_all_day": true,
    "conflict_tijden": "17:34–11:34"
  },
  "N577VX": {
    "no_availability_all_day": true,
    "conflict_tijden": "17:34–11:34"
  },
  "N584VX": {
    "no_availability_all_day": false,
    "conflict_tijden": "17:34–18:35"
  },
  "N585NL": {
    "no_availability_all_day": false,
    "conflict_tijden": "17:34–17:37, 08:00–11:34"
  },
  "N590NL": {
    "no_availability_all_day": false,
    "conflict_tijden": "17:34–18:54"
  },
  "N603PD": {
    "no_availability_all_day": false,
    "conflict_tijden": ""
  },
  "N618KH": {
    "no_availability_all_day": false,
    "conflict_tijden": "08:30–10:30"
  },
  "N633NV": {
    "no_availability_all_day": false,
    "conflict_tijden": "09:45–11:34"
  },
  "N637NV": {
    "no_availability_all_day": false,
    "conflict_tijden": ""
  },
  "N650LK": {
    "no_availability_all_day": true,
    "conflict_tijden": "17:34–11:34"
  },
  "N654KK": {
    "no_availability_all_day": false,
    "conflict_tijden": "07:45–11:34"
  },
  "N654LK": {
    "no_availability_all_day": false,
    "conflict_tijden": ""
  },
  "N657KK": {
    "no_availability_all_day": false,
    "conflict_tijden": "17:34–09:30"
  },
  "N659KK": {
    "no_availability_all_day": false,
    "conflict_tijden": "08:30–11:34"
  },
  "N662KK": {
    "no_availability_all_day": false,
    "conflict_tijden": "07:15–11:34"
  },
  "N664LK": {
    "no_availability_all_day": false,
    "conflict_tijden": "17:34–23:15"
  },
  "N671LK": {
    "no_availability_all_day": false,
    "conflict_tijden": ""
  },
  "N675LK": {
    "no_availability_all_day": false,
    "conflict_tijden": "07:45–11:34"
  },
  "N683SP": {
    "no_availability_all_day": false,
    "conflict_tijden": ""
  },
  "N747KJ": {
    "no_availability_all_day": false,
    "conflict_tijden": ""
  },
  "N800RN": {
    "no_availability_all_day": false,
    "conflict_tijden": ""
  },
  "N806RD": {
    "no_availability_all_day": true,
    "conflict_tijden": "17:34–11:34"
  },
  "N808JV": {
    "no_availability_all_day": true,
    "conflict_tijden": "17:34–11:34"
  },
  "N823JV": {
    "no_availability_all_day": true,
    "conflict_tijden": "17:34–11:34"
  },
  "N824JV": {
    "no_availability_all_day": false,
    "conflict_tijden": "17:34–20:15"
  },
  "N831JV": {
    "no_availability_all_day": true,
    "conflict_tijden": "17:34–11:34"
  },
  "N834KF": {
    "no_availability_all_day": false,
    "conflict_tijden": ""
  },
  "N840KF": {
    "no_availability_all_day": false,
    "conflict_tijden": ""
  },
  "N843RX": {
    "no_availability_all_day": true,
    "conflict_tijden": "17:34–11:34"
  },
  "N880RN": {
    "no_availability_all_day": false,
    "conflict_tijden": "09:00–11:34"
  },
  "N956DH": {
    "no_availability_all_day": false,
    "conflict_tijden": ""
  },
  "N969DH": {
    "no_availability_all_day": false,
    "conflict_tijden": "23:30–11:34"
  },
  "N977DH": {
    "no_availability_all_day": false,
    "conflict_tijden": ""
  },
  "P143TT": {
    "no_availability_all_day": false,
    "conflict_tijden": "07:00–11:34"
  },
  "P145TT": {
    "no_availability_all_day": false,
    "conflict_tijden": "17:34–01:15, 08:30–11:34"
  },
  "P146GX": {
    "no_availability_all_day": false,
    "conflict_tijden": ""
  },
  "P163RT": {
    "no_availability_all_day": false,
    "conflict_tijden": ""
  },
  "P168RT": {
    "no_availability_all_day": false,
    "conflict_tijden": ""
  },
  "P210XX": {
    "no_availability_all_day": false,
    "conflict_tijden": ""
  },
  "P242JZ": {
    "no_availability_all_day": true,
    "conflict_tijden": "17:34–11:34"
  },
  "P255JZ": {
    "no_availability_all_day": false,
    "conflict_tijden": ""
  },
  "P497VB": {
    "no_availability_all_day": false,
    "conflict_tijden": "07:00–11:34"
  },
  "P514GN": {
    "no_availability_all_day": false,
    "conflict_tijden": "18:30–22:30"
  },
  "P611VV": {
    "no_availability_all_day": false,
    "conflict_tijden": "07:45–11:34"
  },
  "P612VV": {
    "no_availability_all_day": false,
    "conflict_tijden": ""
  },
  "P616VV": {
    "no_availability_all_day": false,
    "conflict_tijden": ""
  },
  "P623VV": {
    "no_availability_all_day": false,
    "conflict_tijden": "07:00–11:34"
  },
  "P665ZP": {
    "no_availability_all_day": false,
    "conflict_tijden": ""
  },
  "P667ZP": {
    "no_availability_all_day": false,
    "conflict_tijden": ""
  },
  "P795KN": {
    "no_availability_all_day": false,
    "conflict_tijden": "06:30–11:00"
  },
  "P803KN": {
    "no_availability_all_day": false,
    "conflict_tijden": ""
  },
  "P883SH": {
    "no_availability_all_day": false,
    "conflict_tijden": "17:34–17:35, 08:00–11:34"
  },
  "P987TK": {
    "no_availability_all_day": false,
    "conflict_tijden": "06:00–11:34"
  },
  "P989TK": {
    "no_availability_all_day": false,
    "conflict_tijden": "20:00–11:34"
  },
  "R238BD": {
    "no_availability_all_day": false,
    "conflict_tijden": "06:00–11:34"
  },
  "R240BD": {
    "no_availability_all_day": true,
    "conflict_tijden": "17:34–11:34"
  },
  "R580FP": {
    "no_availability_all_day": false,
    "conflict_tijden": ""
  },
  "R795JB": {
    "no_availability_all_day": false,
    "conflict_tijden": "17:34–19:26, 06:00–11:34"
  },
  "R802JB": {
    "no_availability_all_day": false,
    "conflict_tijden": "17:34–20:00"
  },
  "R806JB": {
    "no_availability_all_day": false,
    "conflict_tijden": "18:45–22:30"
  },
  "R967JS": {
    "no_availability_all_day": false,
    "conflict_tijden": "17:34–00:59"
  },
  "S115SV": {
    "no_availability_all_day": true,
    "conflict_tijden": "17:34–11:34"
  },
  "S120SV": {
    "no_availability_all_day": false,
    "conflict_tijden": ""
  },
  "S136GZ": {
    "no_availability_all_day": false,
    "conflict_tijden": ""
  },
  "S147SV": {
    "no_availability_all_day": true,
    "conflict_tijden": "17:34–11:34"
  },
  "S149SV": {
    "no_availability_all_day": false,
    "conflict_tijden": "10:00–11:34"
  },
  "S262SH": {
    "no_availability_all_day": false,
    "conflict_tijden": "06:15–11:34"
  },
  "S348BT": {
    "no_availability_all_day": false,
    "conflict_tijden": "08:00–11:34"
  },
  "S352BT": {
    "no_availability_all_day": false,
    "conflict_tijden": "18:30–23:30"
  },
  "S353BT": {
    "no_availability_all_day": false,
    "conflict_tijden": "07:00–11:34"
  },
  "S354BT": {
    "no_availability_all_day": false,
    "conflict_tijden": "17:34–21:00"
  },
  "S675TS": {
    "no_availability_all_day": true,
    "conflict_tijden": "17:34–11:34"
  },
  "S683TS": {
    "no_availability_all_day": false,
    "conflict_tijden": "08:45–11:34"
  },
  "S694TS": {
    "no_availability_all_day": false,
    "conflict_tijden": "17:34–19:30"
  },
  "S703TS": {
    "no_availability_all_day": false,
    "conflict_tijden": "17:34–19:00"
  },
  "S704TS": {
    "no_availability_all_day": true,
    "conflict_tijden": "17:34–11:34"
  },
  "S705TS": {
    "no_availability_all_day": false,
    "conflict_tijden": "08:00–11:34"
  },
  "T137DJ": {
    "no_availability_all_day": true,
    "conflict_tijden": "17:34–11:34"
  },
  "T236JG": {
    "no_availability_all_day": false,
    "conflict_tijden": ""
  },
  "T237JG": {
    "no_availability_all_day": false,
    "conflict_tijden": ""
  },
  "T263JG": {
    "no_availability_all_day": false,
    "conflict_tijden": ""
  },
  "T286JV": {
    "no_availability_all_day": true,
    "conflict_tijden": "17:34–11:34"
  },
  "T407JN": {
    "no_availability_all_day": false,
    "conflict_tijden": ""
  },
  "T466KG": {
    "no_availability_all_day": false,
    "conflict_tijden": ""
  },
  "T511BV": {
    "no_availability_all_day": false,
    "conflict_tijden": "09:45–11:34"
  },
  "T557KK": {
    "no_availability_all_day": true,
    "conflict_tijden": "17:34–11:34"
  },
  "T560KK": {
    "no_availability_all_day": true,
    "conflict_tijden": "17:34–11:34"
  },
  "T663JK": {
    "no_availability_all_day": false,
    "conflict_tijden": "17:34–20:00"
  },
  "T694JT": {
    "no_availability_all_day": false,
    "conflict_tijden": "17:34–00:00"
  },
  "T702JT": {
    "no_availability_all_day": false,
    "conflict_tijden": ""
  },
  "T801ZN": {
    "no_availability_all_day": false,
    "conflict_tijden": "07:30–11:34"
  },
  "T810ZN": {
    "no_availability_all_day": false,
    "conflict_tijden": "17:34–19:01"
  },
  "T814ZN": {
    "no_availability_all_day": false,
    "conflict_tijden": "20:00–11:34"
  },
  "T816PB": {
    "no_availability_all_day": false,
    "conflict_tijden": "08:15–11:34"
  },
  "T819ZN": {
    "no_availability_all_day": true,
    "conflict_tijden": "17:34–11:34"
  },
  "T820ZN": {
    "no_availability_all_day": false,
    "conflict_tijden": ""
  },
  "T821PB": {
    "no_availability_all_day": false,
    "conflict_tijden": "19:00–21:45, 07:30–11:34"
  },
  "T825ZN": {
    "no_availability_all_day": false,
    "conflict_tijden": ""
  },
  "T827ZN": {
    "no_availability_all_day": false,
    "conflict_tijden": ""
  },
  "T857DH": {
    "no_availability_all_day": true,
    "conflict_tijden": "17:34–11:34"
  },
  "T875BZ": {
    "no_availability_all_day": false,
    "conflict_tijden": "17:34–19:02"
  },
  "T877DH": {
    "no_availability_all_day": false,
    "conflict_tijden": ""
  },
  "T879DH": {
    "no_availability_all_day": true,
    "conflict_tijden": "17:34–11:34"
  },
  "T883DH": {
    "no_availability_all_day": false,
    "conflict_tijden": "17:34–18:44"
  },
  "T886BZ": {
    "no_availability_all_day": false,
    "conflict_tijden": "17:34–20:45"
  },
  "T935DH": {
    "no_availability_all_day": true,
    "conflict_tijden": "17:34–11:34"
  },
  "T960DH": {
    "no_availability_all_day": true,
    "conflict_tijden": "17:34–11:34"
  },
  "T962DH": {
    "no_availability_all_day": false,
    "conflict_tijden": "19:00–22:30"
  },
  "T979DH": {
    "no_availability_all_day": true,
    "conflict_tijden": "17:34–11:34"
  }
}