{
  "H469LX": {
    "no_availability_all_day": false,
    "conflict_tijden": ""
  },
  "HHV33T": {
    "no_availability_all_day": false,
    "conflict_tijden": "15:31–19:00"
  },
  "HHV38T": {
    "no_availability_all_day": false,
    "conflict_tijden": ""
  },
  "HHV44T": {
    "no_availability_all_day": false,
    "conflict_tijden": "15:31–21:00"
  },
  "HHV50T": {
    "no_availability_all_day": false,
    "conflict_tijden": ""
  },
  "HHV51T": {
    "no_availability_all_day": false,
    "conflict_tijden": "18:00–22:00"
  },
  "HHV55T": {
    "no_availability_all_day": false,
    "conflict_tijden": ""
  },
  "HHV65T": {
    "no_availability_all_day": false,
    "conflict_tijden": ""
  },
  "HHV67T": {
    "no_availability_all_day": false,
    "conflict_tijden": "16:10–18:31"
  },
  "HHV72T": {
    "no_availability_all_day": false,
    "conflict_tijden": "15:31–18:30"
  },
  "HJD81F": {
    "no_availability_all_day": false,
    "conflict_tijden": ""
  },
  "J098JV": {
    "no_availability_all_day": true,
    "conflict_tijden": "15:31–09:31"
  },
  "J601HR": {
    "no_availability_all_day": false,
    "conflict_tijden": ""
  },
  "J609HR": {
    "no_availability_all_day": false,
    "conflict_tijden": ""
  },
  "J615HR": {
    "no_availability_all_day": false,
    "conflict_tijden": "15:31–19:00"
  },
  "J855JH": {
    "no_availability_all_day": false,
    "conflict_tijden": "15:31–17:47"
  },
  "JPD30G": {
    "no_availability_all_day": false,
    "conflict_tijden": ""
  },
  "JPD31G": {
    "no_availability_all_day": false,
    "conflict_tijden": ""
  },
  "JPD32G": {
    "no_availability_all_day": false,
    "conflict_tijden": ""
  },
  "JPD34G": {
    "no_availability_all_day": false,
    "conflict_tijden": "17:45–22:15"
  },
  "JPD36G": {
    "no_availability_all_day": false,
    "conflict_tijden": ""
  },
  "JPD37G": {
    "no_availability_all_day": false,
    "conflict_tijden": "09:00–09:31"
  },
  "JPD39G": {
    "no_availability_all_day": false,
    "conflict_tijden": "08:30–09:31"
  },
  "JPD47G": {
    "no_availability_all_day": false,
    "conflict_tijden": ""
  },
  "JPD51G": {
    "no_availability_all_day": true,
    "conflict_tijden": "15:31–09:31"
  },
  "JPD55G": {
    "no_availability_all_day": false,
    "conflict_tijden": ""
  },
  "JPD65G": {
    "no_availability_all_day": false,
    "conflict_tijden": "16:23–03:00"
  },
  "JPD68G": {
    "no_availability_all_day": false,
    "conflict_tijden": ""
  },
  "JPD70G": {
    "no_availability_all_day": false,
    "conflict_tijden": ""
  },
  "JPD72G": {
    "no_availability_all_day": false,
    "conflict_tijden": ""
  },
  "JPD75G": {
    "no_availability_all_day": false,
    "conflict_tijden": "15:31–23:00"
  },
  "JPD76G": {
    "no_availability_all_day": false,
    "conflict_tijden": "15:31–21:30"
  },
  "JPD80G": {
    "no_availability_all_day": false,
    "conflict_tijden": ""
  },
  "JPD84G": {
    "no_availability_all_day": false,
    "conflict_tijden": ""
  },
  "JPD87G": {
    "no_availability_all_day": false,
    "conflict_tijden": ""
  },
  "JPD93G": {
    "no_availability_all_day": false,
    "conflict_tijden": ""
  },
  "JRH21T": {
    "no_availability_all_day": false,
    "conflict_tijden": "15:31–20:00"
  },
  "JRH24T": {
    "no_availability_all_day": false,
    "conflict_tijden": ""
  },
  "JRH38T": {
    "no_availability_all_day": false,
    "conflict_tijden": ""
  },
  "JRH54T": {
    "no_availability_all_day": false,
    "conflict_tijden": "15:31–16:38"
  },
  "JRH58T": {
    "no_availability_all_day": false,
    "conflict_tijden": "15:31–17:05"
  },
  "JRH61T": {
    "no_availability_all_day": true,
    "conflict_tijden": "15:31–09:31"
  },
  "JRH62T": {
    "no_availability_all_day": false,
    "conflict_tijden": ""
  },
  "JRH68T": {
    "no_availability_all_day": false,
    "conflict_tijden": ""
  },
  "JRH70T": {
    "no_availability_all_day": false,
    "conflict_tijden": ""
  },
  "JRH72T": {
    "no_availability_all_day": false,
    "conflict_tijden": ""
  },
  "JRH74T": {
    "no_availability_all_day": true,
    "conflict_tijden": "15:31–09:31"
  },
  "JRH83T": {
    "no_availability_all_day": false,
    "conflict_tijden": ""
  },
  "JRH85T": {
    "no_availability_all_day": false,
    "conflict_tijden": ""
  },
  "JRZ61S": {
    "no_availability_all_day": false,
    "conflict_tijden": "15:31–20:00"
  },
  "K011JT": {
    "no_availability_all_day": false,
    "conflict_tijden": ""
  },
  "K048FN": {
    "no_availability_all_day": false,
    "conflict_tijden": ""
  },
  "K060FN": {
    "no_availability_all_day": false,
    "conflict_tijden": "15:31–18:19"
  },
  "K094ZF": {
    "no_availability_all_day": false,
    "conflict_tijden": ""
  },
  "K120LN": {
    "no_availability_all_day": false,
    "conflict_tijden": ""
  },
  "K392NP": {
    "no_availability_all_day": false,
    "conflict_tijden": ""
  },
  "K420NP": {
    "no_availability_all_day": false,
    "conflict_tijden": ""
  },
  "K430NP": {
    "no_availability_all_day": false,
    "conflict_tijden": ""
  },
  "K447NP": {
    "no_availability_all_day": false,
    "conflict_tijden": ""
  },
  "K454NP": {
    "no_availability_all_day": false,
    "conflict_tijden": "16:15–17:20"
  },
  "K502FN": {
    "no_availability_all_day": false,
    "conflict_tijden": ""
  },
  "K505JK": {
    "no_availability_all_day": true,
    "conflict_tijden": "15:31–09:31"
  },
  "K507JK": {
    "no_availability_all_day": false,
    "conflict_tijden": "16:10–16:49"
  },
  "K510JK": {
    "no_availability_all_day": false,
    "conflict_tijden": ""
  },
  "K525JK": {
    "no_availability_all_day": false,
    "conflict_tijden": ""
  },
  "K645JH": {
    "no_availability_all_day": true,
    "conflict_tijden": "15:31–09:31"
  },
  "K657JH": {
    "no_availability_all_day": false,
    "conflict_tijden": "15:31–20:00"
  },
  "K811JH": {
    "no_availability_all_day": false,
    "conflict_tijden": ""
  },
  "K816JH": {
    "no_availability_all_day": false,
    "conflict_tijden": ""
  },
  "K966JS": {
    "no_availability_all_day": false,
    "conflict_tijden": "15:31–21:00"
  },
  "K971JS": {
    "no_availability_all_day": true,
    "conflict_tijden": "15:31–09:31"
  },
  "K990JS": {
    "no_availability_all_day": false,
    "conflict_tijden": "21:45–09:31"
  },
  "K994JS": {
    "no_availability_all_day": false,
    "conflict_tijden": "15:31–15:36"
  },
  "L036GG": {
    "no_availability_all_day": false,
    "conflict_tijden": "15:31–19:00"
  },
  "L056GG": {
    "no_availability_all_day": false,
    "conflict_tijden": ""
  },
  "L059ZR": {
    "no_availability_all_day": false,
    "conflict_tijden": ""
  },
  "L085KT": {
    "no_availability_all_day": false,
    "conflict_tijden": ""
  },
  "L089HG": {
    "no_availability_all_day": false,
    "conflict_tijden": ""
  },
  "L091HG": {
    "no_availability_all_day": false,
    "conflict_tijden": ""
  },
  "L097HG": {
    "no_availability_all_day": false,
    "conflict_tijden": "08:00–09:31"
  },
  "L103ZP": {
    "no_availability_all_day": false,
    "conflict_tijden": ""
  },
  "L105ZP": {
    "no_availability_all_day": true,
    "conflict_tijden": "15:31–09:31"
  },
  "L107HG": {
    "no_availability_all_day": false,
    "conflict_tijden": "15:31–16:47"
  },
  "L120JB": {
    "no_availability_all_day": false,
    "conflict_tijden": "15:31–17:21"
  },
  "L246NJ": {
    "no_availability_all_day": false,
    "conflict_tijden": "15:31–19:30"
  },
  "L254NJ": {
    "no_availability_all_day": false,
    "conflict_tijden": ""
  },
  "L416TN": {
    "no_availability_all_day": true,
    "conflict_tijden": "15:31–09:31"
  },
  "L513LF": {
    "no_availability_all_day": false,
    "conflict_tijden": "15:31–17:26"
  },
  "L516LF": {
    "no_availability_all_day": false,
    "conflict_tijden": "15:31–19:15"
  },
  "L566PV": {
    "no_availability_all_day": false,
    "conflict_tijden": "15:31–08:30"
  },
  "L588PV": {
    "no_availability_all_day": false,
    "conflict_tijden": ""
  },
  "L629KP": {
    "no_availability_all_day": true,
    "conflict_tijden": "15:31–09:31"
  },
  "L634KP": {
    "no_availability_all_day": false,
    "conflict_tijden": ""
  },
  "L636KP": {
    "no_availability_all_day": false,
    "conflict_tijden": ""
  },
  "L663GR": {
    "no_availability_all_day": false,
    "conflict_tijden": "15:31–16:27"
  },
  "L665GR": {
    "no_availability_all_day": false,
    "conflict_tijden": "15:31–19:30"
  },
  "L818NR": {
    "no_availability_all_day": false,
    "conflict_tijden": "15:31–17:13, 09:15–09:31"
  },
  "L827NR": {
    "no_availability_all_day": false,
    "conflict_tijden": "15:31–17:39"
  },
  "L828NR": {
    "no_availability_all_day": false,
    "conflict_tijden": ""
  },
  "L865GX": {
    "no_availability_all_day": false,
    "conflict_tijden": ""
  },
  "L879NR": {
    "no_availability_all_day": false,
    "conflict_tijden": "09:00–09:31"
  },
  "L882NR": {
    "no_availability_all_day": false,
    "conflict_tijden": ""
  },
  "L972NL": {
    "no_availability_all_day": false,
    "conflict_tijden": "15:31–20:30, 08:00–09:31"
  },
  "L978NL": {
    "no_availability_all_day": false,
    "conflict_tijden": ""
  },
  "N062JD": {
    "no_availability_all_day": false,
    "conflict_tijden": ""
  },
  "N082KV": {
    "no_availability_all_day": false,
    "conflict_tijden": ""
  },
  "N084KV": {
    "no_availability_all_day": false,
    "conflict_tijden": "08:00–09:31"
  },
  "N089JB": {
    "no_availability_all_day": true,
    "conflict_tijden": "15:31–09:31"
  },
  "N093BR": {
    "no_availability_all_day": false,
    "conflict_tijden": "08:00–09:31"
  },
  "N125PG": {
    "no_availability_all_day": false,
    "conflict_tijden": "17:30–19:30"
  },
  "N137RD": {
    "no_availability_all_day": true,
    "conflict_tijden": "15:31–09:31"
  },
  "N143RD": {
    "no_availability_all_day": false,
    "conflict_tijden": "15:31–17:59"
  },
  "N143SX": {
    "no_availability_all_day": false,
    "conflict_tijden": "15:31–17:02"
  },
  "N145RZ": {
    "no_availability_all_day": false,
    "conflict_tijden": "15:31–19:15"
  },
  "N146RZ": {
    "no_availability_all_day": false,
    "conflict_tijden": ""
  },
  "N148RZ": {
    "no_availability_all_day": false,
    "conflict_tijden": ""
  },
  "N153RZ": {
    "no_availability_all_day": false,
    "conflict_tijden": "15:31–17:59"
  },
  "N155RD": {
    "no_availability_all_day": false,
    "conflict_tijden": "16:51–09:31"
  },
  "N157RD": {
    "no_availability_all_day": false,
    "conflict_tijden": ""
  },
  "N180SF": {
    "no_availability_all_day": false,
    "conflict_tijden": ""
  },
  "N186RD": {
    "no_availability_all_day": false,
    "conflict_tijden": "09:00–09:31"
  },
  "N191RD": {
    "no_availability_all_day": true,
    "conflict_tijden": "15:31–09:31"
  },
  "N200BH": {
    "no_availability_all_day": false,
    "conflict_tijden": ""
  },
  "N200HV": {
    "no_availability_all_day": false,
    "conflict_tijden": ""
  },
  "N201HV": {
    "no_availability_all_day": false,
    "conflict_tijden": "15:31–17:27"
  },
  "N204HV": {
    "no_availability_all_day": true,
    "conflict_tijden": "15:31–09:31"
  },
  "N221PF": {
    "no_availability_all_day": false,
    "conflict_tijden": "15:31–23:15"
  },
  "N236PF": {
    "no_availability_all_day": false,
    "conflict_tijden": "18:45–01:45, 06:30–09:31"
  },
  "N249VT": {
    "no_availability_all_day": false,
    "conflict_tijden": "15:31–23:00, 08:00–09:31"
  },
  "N250VT": {
    "no_availability_all_day": true,
    "conflict_tijden": "15:31–09:31"
  },
  "N254VT": {
    "no_availability_all_day": false,
    "conflict_tijden": "15:31–22:45"
  },
  "N269KS": {
    "no_availability_all_day": true,
    "conflict_tijden": "15:31–09:31"
  },
  "N289PS": {
    "no_availability_all_day": false,
    "conflict_tijden": "08:00–09:31"
  },
  "N291PS": {
    "no_availability_all_day": false,
    "conflict_tijden": "21:15–00:00"
  },
  "N296VT": {
    "no_availability_all_day": false,
    "conflict_tijden": "15:31–15:39"
  },
  "N315VT": {
    "no_availability_all_day": false,
    "conflict_tijden": ""
  },
  "N318PS": {
    "no_availability_all_day": false,
    "conflict_tijden": "20:15–00:15"
  },
  "N336SF": {
    "no_availability_all_day": false,
    "conflict_tijden": "15:39–17:30"
  },
  "N340VT": {
    "no_availability_all_day": true,
    "conflict_tijden": "15:31–09:31"
  },
  "N350SF": {
    "no_availability_all_day": true,
    "conflict_tijden": "15:31–09:31"
  },
  "N365RG": {
    "no_availability_all_day": false,
    "conflict_tijden": ""
  },
  "N368RG": {
    "no_availability_all_day": false,
    "conflict_tijden": "15:31–00:30"
  },
  "N386VT": {
    "no_availability_all_day": true,
    "conflict_tijden": "15:31–09:31"
  },
  "N387VT": {
    "no_availability_all_day": true,
    "conflict_tijden": "15:31–09:31"
  },
  "N392LD": {
    "no_availability_all_day": false,
    "conflict_tijden": "15:31–18:10, 18:30–21:30, 07:00–09:31"
  },
  "N393LD": {
    "no_availability_all_day": true,
    "conflict_tijden": "15:31–09:31"
  },
  "N400LD": {
    "no_availability_all_day": false,
    "conflict_tijden": "15:31–18:20"
  },
  "N403VT": {
    "no_availability_all_day": true,
    "conflict_tijden": "15:31–09:31"
  },
  "N406LD": {
    "no_availability_all_day": false,
    "conflict_tijden": "15:31–20:00, 08:00–09:31"
  },
  "N408LD": {
    "no_availability_all_day": false,
    "conflict_tijden": "15:31–21:00"
  },
  "N413BF": {
    "no_availability_all_day": false,
    "conflict_tijden": "15:31–15:49"
  },
  "N413LD": {
    "no_availability_all_day": false,
    "conflict_tijden": ""
  },
  "N418LD": {
    "no_availability_all_day": false,
    "conflict_tijden": "17:30–21:30"
  },
  "N419LD": {
    "no_availability_all_day": true,
    "conflict_tijden": "15:31–09:31"
  },
  "N457NR": {
    "no_availability_all_day": false,
    "conflict_tijden": ""
  },
  "N464NR": {
    "no_availability_all_day": false,
    "conflict_tijden": "15:31–18:04"
  },
  "N483NR": {
    "no_availability_all_day": false,
    "conflict_tijden": ""
  },
  "N488NR": {
    "no_availability_all_day": false,
    "conflict_tijden": "20:30–23:30, 07:00–09:31"
  },
  "N490NR": {
    "no_availability_all_day": false,
    "conflict_tijden": ""
  },
  "N491NR": {
    "no_availability_all_day": false,
    "conflict_tijden": "09:30–09:31"
  },
  "N522VX": {
    "no_availability_all_day": false,
    "conflict_tijden": "15:31–21:00"
  },
  "N536VX": {
    "no_availability_all_day": false,
    "conflict_tijden": ""
  },
  "N542VX": {
    "no_availability_all_day": false,
    "conflict_tijden": ""
  },
  "N560VX": {
    "no_availability_all_day": true,
    "conflict_tijden": "15:31–09:31"
  },
  "N564VX": {
    "no_availability_all_day": true,
    "conflict_tijden": "15:31–09:31"
  },
  "N565VX": {
    "no_availability_all_day": false,
    "conflict_tijden": ""
  },
  "N577VX": {
    "no_availability_all_day": true,
    "conflict_tijden": "15:31–09:31"
  },
  "N584VX": {
    "no_availability_all_day": true,
    "conflict_tijden": "15:31–09:31"
  },
  "N587NL": {
    "no_availability_all_day": false,
    "conflict_tijden": "15:31–19:00"
  },
  "N590NL": {
    "no_availability_all_day": false,
    "conflict_tijden": ""
  },
  "N603PD": {
    "no_availability_all_day": true,
    "conflict_tijden": "15:31–09:31"
  },
  "N605NV": {
    "no_availability_all_day": false,
    "conflict_tijden": ""
  },
  "N607PD": {
    "no_availability_all_day": true,
    "conflict_tijden": "15:31–09:31"
  },
  "N647NV": {
    "no_availability_all_day": false,
    "conflict_tijden": "15:31–18:30"
  },
  "N654KK": {
    "no_availability_all_day": false,
    "conflict_tijden": ""
  },
  "N654LK": {
    "no_availability_all_day": false,
    "conflict_tijden": ""
  },
  "N672LK": {
    "no_availability_all_day": false,
    "conflict_tijden": "18:30–22:15"
  },
  "N675LK": {
    "no_availability_all_day": false,
    "conflict_tijden": "15:31–18:22"
  },
  "N747KJ": {
    "no_availability_all_day": false,
    "conflict_tijden": "15:31–17:39, 09:00–09:31"
  },
  "N813JV": {
    "no_availability_all_day": false,
    "conflict_tijden": ""
  },
  "N824JV": {
    "no_availability_all_day": false,
    "conflict_tijden": "15:31–21:15"
  },
  "N834KF": {
    "no_availability_all_day": false,
    "conflict_tijden": "15:31–16:48"
  },
  "N853PN": {
    "no_availability_all_day": false,
    "conflict_tijden": "15:31–20:00"
  },
  "N866RN": {
    "no_availability_all_day": true,
    "conflict_tijden": "15:31–09:31"
  },
  "N880RN": {
    "no_availability_all_day": true,
    "conflict_tijden": "15:31–09:31"
  },
  "P143TT": {
    "no_availability_all_day": false,
    "conflict_tijden": ""
  },
  "P163RT": {
    "no_availability_all_day": true,
    "conflict_tijden": "15:31–09:31"
  },
  "P241JZ": {
    "no_availability_all_day": false,
    "conflict_tijden": "15:31–17:35"
  },
  "P252JZ": {
    "no_availability_all_day": false,
    "conflict_tijden": "15:31–17:23, 22:15–02:15"
  },
  "P306PR": {
    "no_availability_all_day": false,
    "conflict_tijden": ""
  },
  "P322GR": {
    "no_availability_all_day": false,
    "conflict_tijden": ""
  },
  "P418LP": {
    "no_availability_all_day": false,
    "conflict_tijden": "15:31–20:00"
  },
  "P422LP": {
    "no_availability_all_day": false,
    "conflict_tijden": "15:31–15:39"
  },
  "P498VB": {
    "no_availability_all_day": false,
    "conflict_tijden": ""
  },
  "P617VV": {
    "no_availability_all_day": false,
    "conflict_tijden": "15:31–17:57"
  },
  "P620VV": {
    "no_availability_all_day": false,
    "conflict_tijden": "15:31–21:00"
  },
  "P666ZP": {
    "no_availability_all_day": false,
    "conflict_tijden": "15:31–21:00, 09:30–09:31"
  },
  "P667ZP": {
    "no_availability_all_day": true,
    "conflict_tijden": "15:31–09:31"
  },
  "P788TV": {
    "no_availability_all_day": false,
    "conflict_tijden": "08:15–09:31"
  },
  "P804KN": {
    "no_availability_all_day": false,
    "conflict_tijden": ""
  },
  "P804ZL": {
    "no_availability_all_day": false,
    "conflict_tijden": ""
  },
  "P883VH": {
    "no_availability_all_day": false,
    "conflict_tijden": "15:31–22:15"
  },
  "P885VH": {
    "no_availability_all_day": false,
    "conflict_tijden": "15:31–20:30"
  },
  "R793TJ": {
    "no_availability_all_day": false,
    "conflict_tijden": "15:31–21:45"
  },
  "R801JB": {
    "no_availability_all_day": true,
    "conflict_tijden": "15:31–09:31"
  },
  "R976JS": {
    "no_availability_all_day": false,
    "conflict_tijden": "15:31–18:23, 09:00–09:31"
  },
  "S008KK": {
    "no_availability_all_day": false,
    "conflict_tijden": ""
  },
  "S091SV": {
    "no_availability_all_day": false,
    "conflict_tijden": "15:31–17:29"
  },
  "S103SV": {
    "no_availability_all_day": true,
    "conflict_tijden": "15:31–09:31"
  },
  "S108SV": {
    "no_availability_all_day": false,
    "conflict_tijden": "15:31–17:02"
  },
  "S135GZ": {
    "no_availability_all_day": false,
    "conflict_tijden": ""
  },
  "S147SV": {
    "no_availability_all_day": false,
    "conflict_tijden": "15:31–23:30"
  },
  "S264SH": {
    "no_availability_all_day": false,
    "conflict_tijden": ""
  },
  "S348BT": {
    "no_availability_all_day": false,
    "conflict_tijden": "15:31–17:19"
  },
  "S351BT": {
    "no_availability_all_day": false,
    "conflict_tijden": "16:00–17:40"
  },
  "S353BT": {
    "no_availability_all_day": false,
    "conflict_tijden": "15:31–17:18"
  },
  "S357BT": {
    "no_availability_all_day": true,
    "conflict_tijden": "15:31–09:31"
  },
  "S358BT": {
    "no_availability_all_day": true,
    "conflict_tijden": "15:31–09:31"
  },
  "S675TS": {
    "no_availability_all_day": false,
    "conflict_tijden": ""
  },
  "S683TS": {
    "no_availability_all_day": false,
    "conflict_tijden": "20:15–23:45"
  },
  "S694TS": {
    "no_availability_all_day": false,
    "conflict_tijden": "09:00–09:31"
  },
  "S705TS": {
    "no_availability_all_day": false,
    "conflict_tijden": "15:31–23:45"
  },
  "S710TS": {
    "no_availability_all_day": false,
    "conflict_tijden": ""
  },
  "S712TS": {
    "no_availability_all_day": false,
    "conflict_tijden": ""
  },
  "T140DJ": {
    "no_availability_all_day": false,
    "conflict_tijden": "15:31–20:30"
  },
  "T221JR": {
    "no_availability_all_day": true,
    "conflict_tijden": "15:31–09:31"
  },
  "T288JV": {
    "no_availability_all_day": false,
    "conflict_tijden": "16:00–17:22, 09:00–09:31"
  },
  "T462JJ": {
    "no_availability_all_day": false,
    "conflict_tijden": "15:31–20:00"
  },
  "T468KG": {
    "no_availability_all_day": false,
    "conflict_tijden": ""
  },
  "T557KK": {
    "no_availability_all_day": false,
    "conflict_tijden": "17:12–20:00, 09:00–09:31"
  },
  "T560KK": {
    "no_availability_all_day": true,
    "conflict_tijden": "15:31–09:31"
  },
  "T705JT": {
    "no_availability_all_day": false,
    "conflict_tijden": "15:31–19:15"
  },
  "T799ZN": {
    "no_availability_all_day": false,
    "conflict_tijden": "15:31–16:49"
  },
  "T802ZN": {
    "no_availability_all_day": false,
    "conflict_tijden": ""
  },
  "T805ZN": {
    "no_availability_all_day": true,
    "conflict_tijden": "15:31–09:31"
  },
  "T810ZN": {
    "no_availability_all_day": false,
    "conflict_tijden": "15:31–20:00"
  },
  "T814ZN": {
    "no_availability_all_day": false,
    "conflict_tijden": ""
  },
  "T815ZN": {
    "no_availability_all_day": false,
    "conflict_tijden": ""
  },
  "T817PB": {
    "no_availability_all_day": false,
    "conflict_tijden": ""
  },
  "T867KN": {
    "no_availability_all_day": false,
    "conflict_tijden": "15:31–17:05"
  },
  "T874DH": {
    "no_availability_all_day": false,
    "conflict_tijden": ""
  },
  "T877DH": {
    "no_availability_all_day": false,
    "conflict_tijden": "15:31–00:59"
  },
  "T879BZ": {
    "no_availability_all_day": true,
    "conflict_tijden": "15:31–09:31"
  },
  "T882BZ": {
    "no_availability_all_day": false,
    "conflict_tijden": ""
  },
  "T979DH": {
    "no_availability_all_day": true,
    "conflict_tijden": "15:31–09:31"
  },
  "X341KR": {
    "no_availability_all_day": false,
    "conflict_tijden": "09:00–09:31"
  }
}